{
  "id": 2611,
  "title": "[Halo] Sylvania PAR38 120V (B: 13.4%)",
  "indices": {
    "ipi": 0.94,
    "msi": 0.29,
    "sli": 0.52,
    "percentBlue": 0.134
  },
  "metaData": {
    "category": "Halo",
    "brand": "Sylvania",
    "lampType": "PAR38"
  },
  "spectralData": [
    {
      "wavelength": 273,
      "relativeIntensity": 0
    },
    {
      "wavelength": 273.5,
      "relativeIntensity": 0
    },
    {
      "wavelength": 274,
      "relativeIntensity": 0
    },
    {
      "wavelength": 274.5,
      "relativeIntensity": 0
    },
    {
      "wavelength": 275,
      "relativeIntensity": 0
    },
    {
      "wavelength": 275.5,
      "relativeIntensity": 0
    },
    {
      "wavelength": 276,
      "relativeIntensity": 0
    },
    {
      "wavelength": 276.5,
      "relativeIntensity": 0
    },
    {
      "wavelength": 277,
      "relativeIntensity": 0
    },
    {
      "wavelength": 277.5,
      "relativeIntensity": 0
    },
    {
      "wavelength": 278,
      "relativeIntensity": 0
    },
    {
      "wavelength": 278.5,
      "relativeIntensity": 0
    },
    {
      "wavelength": 279,
      "relativeIntensity": 0
    },
    {
      "wavelength": 279.5,
      "relativeIntensity": 0
    },
    {
      "wavelength": 280,
      "relativeIntensity": 0
    },
    {
      "wavelength": 280.5,
      "relativeIntensity": 0
    },
    {
      "wavelength": 281,
      "relativeIntensity": 0
    },
    {
      "wavelength": 281.5,
      "relativeIntensity": 0
    },
    {
      "wavelength": 282,
      "relativeIntensity": 0
    },
    {
      "wavelength": 282.5,
      "relativeIntensity": 0
    },
    {
      "wavelength": 283,
      "relativeIntensity": 0
    },
    {
      "wavelength": 283.5,
      "relativeIntensity": 0
    },
    {
      "wavelength": 284,
      "relativeIntensity": 0
    },
    {
      "wavelength": 284.5,
      "relativeIntensity": 0
    },
    {
      "wavelength": 285,
      "relativeIntensity": 0
    },
    {
      "wavelength": 285.5,
      "relativeIntensity": 0
    },
    {
      "wavelength": 286,
      "relativeIntensity": 0
    },
    {
      "wavelength": 286.5,
      "relativeIntensity": 0
    },
    {
      "wavelength": 287,
      "relativeIntensity": 0
    },
    {
      "wavelength": 287.5,
      "relativeIntensity": 0
    },
    {
      "wavelength": 288,
      "relativeIntensity": 0
    },
    {
      "wavelength": 288.5,
      "relativeIntensity": 0
    },
    {
      "wavelength": 289,
      "relativeIntensity": 0
    },
    {
      "wavelength": 289.5,
      "relativeIntensity": 0
    },
    {
      "wavelength": 290,
      "relativeIntensity": 0
    },
    {
      "wavelength": 290.5,
      "relativeIntensity": 0
    },
    {
      "wavelength": 291,
      "relativeIntensity": 0
    },
    {
      "wavelength": 291.5,
      "relativeIntensity": 0
    },
    {
      "wavelength": 292,
      "relativeIntensity": 0
    },
    {
      "wavelength": 292.5,
      "relativeIntensity": 0
    },
    {
      "wavelength": 293,
      "relativeIntensity": 0
    },
    {
      "wavelength": 293.5,
      "relativeIntensity": 0
    },
    {
      "wavelength": 294,
      "relativeIntensity": 0
    },
    {
      "wavelength": 294.5,
      "relativeIntensity": 0
    },
    {
      "wavelength": 295,
      "relativeIntensity": 0
    },
    {
      "wavelength": 295.5,
      "relativeIntensity": 0
    },
    {
      "wavelength": 296,
      "relativeIntensity": 0
    },
    {
      "wavelength": 296.5,
      "relativeIntensity": 0
    },
    {
      "wavelength": 297,
      "relativeIntensity": 0
    },
    {
      "wavelength": 297.5,
      "relativeIntensity": 0
    },
    {
      "wavelength": 298,
      "relativeIntensity": 0
    },
    {
      "wavelength": 298.5,
      "relativeIntensity": 0
    },
    {
      "wavelength": 299,
      "relativeIntensity": 0
    },
    {
      "wavelength": 299.5,
      "relativeIntensity": 0
    },
    {
      "wavelength": 300,
      "relativeIntensity": 0.00017907
    },
    {
      "wavelength": 300.5,
      "relativeIntensity": 0.00047324
    },
    {
      "wavelength": 301,
      "relativeIntensity": 0.00043085
    },
    {
      "wavelength": 301.5,
      "relativeIntensity": 0.00045345
    },
    {
      "wavelength": 302,
      "relativeIntensity": 0.00050122
    },
    {
      "wavelength": 302.5,
      "relativeIntensity": 0.00053738
    },
    {
      "wavelength": 303,
      "relativeIntensity": 0.00057645
    },
    {
      "wavelength": 303.5,
      "relativeIntensity": 0.00054438
    },
    {
      "wavelength": 304,
      "relativeIntensity": 0.00054417
    },
    {
      "wavelength": 304.5,
      "relativeIntensity": 0.00055342
    },
    {
      "wavelength": 305,
      "relativeIntensity": 0.00051391
    },
    {
      "wavelength": 305.5,
      "relativeIntensity": 0.00050774
    },
    {
      "wavelength": 306,
      "relativeIntensity": 0.0004859
    },
    {
      "wavelength": 306.5,
      "relativeIntensity": 0.00050187
    },
    {
      "wavelength": 307,
      "relativeIntensity": 0.00055933
    },
    {
      "wavelength": 307.5,
      "relativeIntensity": 0.00063903
    },
    {
      "wavelength": 308,
      "relativeIntensity": 0.00067231
    },
    {
      "wavelength": 308.5,
      "relativeIntensity": 0.00065722
    },
    {
      "wavelength": 309,
      "relativeIntensity": 0.00064118
    },
    {
      "wavelength": 309.5,
      "relativeIntensity": 0.00057082
    },
    {
      "wavelength": 310,
      "relativeIntensity": 0.00055383
    },
    {
      "wavelength": 310.5,
      "relativeIntensity": 0.00060549
    },
    {
      "wavelength": 311,
      "relativeIntensity": 0.00062442
    },
    {
      "wavelength": 311.5,
      "relativeIntensity": 0.00065022
    },
    {
      "wavelength": 312,
      "relativeIntensity": 0.00066585
    },
    {
      "wavelength": 312.5,
      "relativeIntensity": 0.0006734
    },
    {
      "wavelength": 313,
      "relativeIntensity": 0.00069611
    },
    {
      "wavelength": 313.5,
      "relativeIntensity": 0.00070883
    },
    {
      "wavelength": 314,
      "relativeIntensity": 0.00071514
    },
    {
      "wavelength": 314.5,
      "relativeIntensity": 0.00073206
    },
    {
      "wavelength": 315,
      "relativeIntensity": 0.0007478
    },
    {
      "wavelength": 315.5,
      "relativeIntensity": 0.00075902
    },
    {
      "wavelength": 316,
      "relativeIntensity": 0.00073628
    },
    {
      "wavelength": 316.5,
      "relativeIntensity": 0.00071988
    },
    {
      "wavelength": 317,
      "relativeIntensity": 0.00072285
    },
    {
      "wavelength": 317.5,
      "relativeIntensity": 0.00082626
    },
    {
      "wavelength": 318,
      "relativeIntensity": 0.00088589
    },
    {
      "wavelength": 318.5,
      "relativeIntensity": 0.00089348
    },
    {
      "wavelength": 319,
      "relativeIntensity": 0.00091062
    },
    {
      "wavelength": 319.5,
      "relativeIntensity": 0.00088485
    },
    {
      "wavelength": 320,
      "relativeIntensity": 0.00092563
    },
    {
      "wavelength": 320.5,
      "relativeIntensity": 0.00097481
    },
    {
      "wavelength": 321,
      "relativeIntensity": 0.0010642
    },
    {
      "wavelength": 321.5,
      "relativeIntensity": 0.0011042
    },
    {
      "wavelength": 322,
      "relativeIntensity": 0.001078
    },
    {
      "wavelength": 322.5,
      "relativeIntensity": 0.0011204
    },
    {
      "wavelength": 323,
      "relativeIntensity": 0.0010773
    },
    {
      "wavelength": 323.5,
      "relativeIntensity": 0.0010279
    },
    {
      "wavelength": 324,
      "relativeIntensity": 0.00098797
    },
    {
      "wavelength": 324.5,
      "relativeIntensity": 0.00096589
    },
    {
      "wavelength": 325,
      "relativeIntensity": 0.0010089
    },
    {
      "wavelength": 325.5,
      "relativeIntensity": 0.0010854
    },
    {
      "wavelength": 326,
      "relativeIntensity": 0.0011541
    },
    {
      "wavelength": 326.5,
      "relativeIntensity": 0.0011509
    },
    {
      "wavelength": 327,
      "relativeIntensity": 0.0011343
    },
    {
      "wavelength": 327.5,
      "relativeIntensity": 0.0011483
    },
    {
      "wavelength": 328,
      "relativeIntensity": 0.0012051
    },
    {
      "wavelength": 328.5,
      "relativeIntensity": 0.0012821
    },
    {
      "wavelength": 329,
      "relativeIntensity": 0.001319
    },
    {
      "wavelength": 329.5,
      "relativeIntensity": 0.0013382
    },
    {
      "wavelength": 330,
      "relativeIntensity": 0.0013241
    },
    {
      "wavelength": 330.5,
      "relativeIntensity": 0.0013192
    },
    {
      "wavelength": 331,
      "relativeIntensity": 0.0013589
    },
    {
      "wavelength": 331.5,
      "relativeIntensity": 0.0013972
    },
    {
      "wavelength": 332,
      "relativeIntensity": 0.0014497
    },
    {
      "wavelength": 332.5,
      "relativeIntensity": 0.0014972
    },
    {
      "wavelength": 333,
      "relativeIntensity": 0.0015147
    },
    {
      "wavelength": 333.5,
      "relativeIntensity": 0.0015049
    },
    {
      "wavelength": 334,
      "relativeIntensity": 0.0014727
    },
    {
      "wavelength": 334.5,
      "relativeIntensity": 0.0014331
    },
    {
      "wavelength": 335,
      "relativeIntensity": 0.0014285
    },
    {
      "wavelength": 335.5,
      "relativeIntensity": 0.0014729
    },
    {
      "wavelength": 336,
      "relativeIntensity": 0.0015316
    },
    {
      "wavelength": 336.5,
      "relativeIntensity": 0.0016512
    },
    {
      "wavelength": 337,
      "relativeIntensity": 0.0017773
    },
    {
      "wavelength": 337.5,
      "relativeIntensity": 0.0018887
    },
    {
      "wavelength": 338,
      "relativeIntensity": 0.0019485
    },
    {
      "wavelength": 338.5,
      "relativeIntensity": 0.0019409
    },
    {
      "wavelength": 339,
      "relativeIntensity": 0.0019659
    },
    {
      "wavelength": 339.5,
      "relativeIntensity": 0.0019384
    },
    {
      "wavelength": 340,
      "relativeIntensity": 0.0019761
    },
    {
      "wavelength": 340.5,
      "relativeIntensity": 0.0020169
    },
    {
      "wavelength": 341,
      "relativeIntensity": 0.001996
    },
    {
      "wavelength": 341.5,
      "relativeIntensity": 0.0020705
    },
    {
      "wavelength": 342,
      "relativeIntensity": 0.0021028
    },
    {
      "wavelength": 342.5,
      "relativeIntensity": 0.0021427
    },
    {
      "wavelength": 343,
      "relativeIntensity": 0.0021935
    },
    {
      "wavelength": 343.5,
      "relativeIntensity": 0.0022157
    },
    {
      "wavelength": 344,
      "relativeIntensity": 0.0022726
    },
    {
      "wavelength": 344.5,
      "relativeIntensity": 0.0023537
    },
    {
      "wavelength": 345,
      "relativeIntensity": 0.0024148
    },
    {
      "wavelength": 345.5,
      "relativeIntensity": 0.0024568
    },
    {
      "wavelength": 346,
      "relativeIntensity": 0.0024931
    },
    {
      "wavelength": 346.5,
      "relativeIntensity": 0.0025233
    },
    {
      "wavelength": 347,
      "relativeIntensity": 0.0025639
    },
    {
      "wavelength": 347.5,
      "relativeIntensity": 0.0026082
    },
    {
      "wavelength": 348,
      "relativeIntensity": 0.0026622
    },
    {
      "wavelength": 348.5,
      "relativeIntensity": 0.0026942
    },
    {
      "wavelength": 349,
      "relativeIntensity": 0.0027504
    },
    {
      "wavelength": 349.5,
      "relativeIntensity": 0.002843
    },
    {
      "wavelength": 350,
      "relativeIntensity": 0.0029042
    },
    {
      "wavelength": 350.5,
      "relativeIntensity": 0.0029666
    },
    {
      "wavelength": 351,
      "relativeIntensity": 0.0029694
    },
    {
      "wavelength": 351.5,
      "relativeIntensity": 0.0029547
    },
    {
      "wavelength": 352,
      "relativeIntensity": 0.0029681
    },
    {
      "wavelength": 352.5,
      "relativeIntensity": 0.0030041
    },
    {
      "wavelength": 353,
      "relativeIntensity": 0.0031153
    },
    {
      "wavelength": 353.5,
      "relativeIntensity": 0.0031597
    },
    {
      "wavelength": 354,
      "relativeIntensity": 0.0032141
    },
    {
      "wavelength": 354.5,
      "relativeIntensity": 0.0032386
    },
    {
      "wavelength": 355,
      "relativeIntensity": 0.0032571
    },
    {
      "wavelength": 355.5,
      "relativeIntensity": 0.0033967
    },
    {
      "wavelength": 356,
      "relativeIntensity": 0.0034867
    },
    {
      "wavelength": 356.5,
      "relativeIntensity": 0.0035795
    },
    {
      "wavelength": 357,
      "relativeIntensity": 0.0036501
    },
    {
      "wavelength": 357.5,
      "relativeIntensity": 0.0036619
    },
    {
      "wavelength": 358,
      "relativeIntensity": 0.0037021
    },
    {
      "wavelength": 358.5,
      "relativeIntensity": 0.0037606
    },
    {
      "wavelength": 359,
      "relativeIntensity": 0.003806
    },
    {
      "wavelength": 359.5,
      "relativeIntensity": 0.0038205
    },
    {
      "wavelength": 360,
      "relativeIntensity": 0.0038434
    },
    {
      "wavelength": 360.5,
      "relativeIntensity": 0.0039295
    },
    {
      "wavelength": 361,
      "relativeIntensity": 0.0040106
    },
    {
      "wavelength": 361.5,
      "relativeIntensity": 0.0040967
    },
    {
      "wavelength": 362,
      "relativeIntensity": 0.0041553
    },
    {
      "wavelength": 362.5,
      "relativeIntensity": 0.0041656
    },
    {
      "wavelength": 363,
      "relativeIntensity": 0.0042433
    },
    {
      "wavelength": 363.5,
      "relativeIntensity": 0.0043291
    },
    {
      "wavelength": 364,
      "relativeIntensity": 0.0045315
    },
    {
      "wavelength": 364.5,
      "relativeIntensity": 0.0046955
    },
    {
      "wavelength": 365,
      "relativeIntensity": 0.0048196
    },
    {
      "wavelength": 365.5,
      "relativeIntensity": 0.0049584
    },
    {
      "wavelength": 366,
      "relativeIntensity": 0.0049012
    },
    {
      "wavelength": 366.5,
      "relativeIntensity": 0.004876
    },
    {
      "wavelength": 367,
      "relativeIntensity": 0.0048606
    },
    {
      "wavelength": 367.5,
      "relativeIntensity": 0.0048099
    },
    {
      "wavelength": 368,
      "relativeIntensity": 0.0048975
    },
    {
      "wavelength": 368.5,
      "relativeIntensity": 0.0049968
    },
    {
      "wavelength": 369,
      "relativeIntensity": 0.0050868
    },
    {
      "wavelength": 369.5,
      "relativeIntensity": 0.005222
    },
    {
      "wavelength": 370,
      "relativeIntensity": 0.00535
    },
    {
      "wavelength": 370.5,
      "relativeIntensity": 0.0054901
    },
    {
      "wavelength": 371,
      "relativeIntensity": 0.0056069
    },
    {
      "wavelength": 371.5,
      "relativeIntensity": 0.0056506
    },
    {
      "wavelength": 372,
      "relativeIntensity": 0.0056963
    },
    {
      "wavelength": 372.5,
      "relativeIntensity": 0.0057535
    },
    {
      "wavelength": 373,
      "relativeIntensity": 0.0058419
    },
    {
      "wavelength": 373.5,
      "relativeIntensity": 0.0059691
    },
    {
      "wavelength": 374,
      "relativeIntensity": 0.006041
    },
    {
      "wavelength": 374.5,
      "relativeIntensity": 0.0061562
    },
    {
      "wavelength": 375,
      "relativeIntensity": 0.0062886
    },
    {
      "wavelength": 375.5,
      "relativeIntensity": 0.0063688
    },
    {
      "wavelength": 376,
      "relativeIntensity": 0.0064266
    },
    {
      "wavelength": 376.5,
      "relativeIntensity": 0.0064655
    },
    {
      "wavelength": 377,
      "relativeIntensity": 0.0065361
    },
    {
      "wavelength": 377.5,
      "relativeIntensity": 0.0066551
    },
    {
      "wavelength": 378,
      "relativeIntensity": 0.0067313
    },
    {
      "wavelength": 378.5,
      "relativeIntensity": 0.0067733
    },
    {
      "wavelength": 379,
      "relativeIntensity": 0.0067852
    },
    {
      "wavelength": 379.5,
      "relativeIntensity": 0.0068758
    },
    {
      "wavelength": 380,
      "relativeIntensity": 0.0070454
    },
    {
      "wavelength": 380.5,
      "relativeIntensity": 0.007254
    },
    {
      "wavelength": 381,
      "relativeIntensity": 0.0074344
    },
    {
      "wavelength": 381.5,
      "relativeIntensity": 0.0075535
    },
    {
      "wavelength": 382,
      "relativeIntensity": 0.0076845
    },
    {
      "wavelength": 382.5,
      "relativeIntensity": 0.0077705
    },
    {
      "wavelength": 383,
      "relativeIntensity": 0.0078297
    },
    {
      "wavelength": 383.5,
      "relativeIntensity": 0.0079263
    },
    {
      "wavelength": 384,
      "relativeIntensity": 0.0079813
    },
    {
      "wavelength": 384.5,
      "relativeIntensity": 0.008092
    },
    {
      "wavelength": 385,
      "relativeIntensity": 0.0082221
    },
    {
      "wavelength": 385.5,
      "relativeIntensity": 0.0083187
    },
    {
      "wavelength": 386,
      "relativeIntensity": 0.0084057
    },
    {
      "wavelength": 386.5,
      "relativeIntensity": 0.0085209
    },
    {
      "wavelength": 387,
      "relativeIntensity": 0.0085956
    },
    {
      "wavelength": 387.5,
      "relativeIntensity": 0.0087073
    },
    {
      "wavelength": 388,
      "relativeIntensity": 0.0088363
    },
    {
      "wavelength": 388.5,
      "relativeIntensity": 0.0090004
    },
    {
      "wavelength": 389,
      "relativeIntensity": 0.0091531
    },
    {
      "wavelength": 389.5,
      "relativeIntensity": 0.0093083
    },
    {
      "wavelength": 390,
      "relativeIntensity": 0.0094261
    },
    {
      "wavelength": 390.5,
      "relativeIntensity": 0.0095556
    },
    {
      "wavelength": 391,
      "relativeIntensity": 0.0096192
    },
    {
      "wavelength": 391.5,
      "relativeIntensity": 0.0097413
    },
    {
      "wavelength": 392,
      "relativeIntensity": 0.0098353
    },
    {
      "wavelength": 392.5,
      "relativeIntensity": 0.0098881
    },
    {
      "wavelength": 393,
      "relativeIntensity": 0.0099547
    },
    {
      "wavelength": 393.5,
      "relativeIntensity": 0.010043
    },
    {
      "wavelength": 394,
      "relativeIntensity": 0.010148
    },
    {
      "wavelength": 394.5,
      "relativeIntensity": 0.010308
    },
    {
      "wavelength": 395,
      "relativeIntensity": 0.010468
    },
    {
      "wavelength": 395.5,
      "relativeIntensity": 0.010586
    },
    {
      "wavelength": 396,
      "relativeIntensity": 0.010684
    },
    {
      "wavelength": 396.5,
      "relativeIntensity": 0.010761
    },
    {
      "wavelength": 397,
      "relativeIntensity": 0.01084
    },
    {
      "wavelength": 397.5,
      "relativeIntensity": 0.010953
    },
    {
      "wavelength": 398,
      "relativeIntensity": 0.011164
    },
    {
      "wavelength": 398.5,
      "relativeIntensity": 0.011344
    },
    {
      "wavelength": 399,
      "relativeIntensity": 0.011477
    },
    {
      "wavelength": 399.5,
      "relativeIntensity": 0.0116
    },
    {
      "wavelength": 400,
      "relativeIntensity": 0.011676
    },
    {
      "wavelength": 400.5,
      "relativeIntensity": 0.011756
    },
    {
      "wavelength": 401,
      "relativeIntensity": 0.011912
    },
    {
      "wavelength": 401.5,
      "relativeIntensity": 0.012059
    },
    {
      "wavelength": 402,
      "relativeIntensity": 0.012196
    },
    {
      "wavelength": 402.5,
      "relativeIntensity": 0.012352
    },
    {
      "wavelength": 403,
      "relativeIntensity": 0.012458
    },
    {
      "wavelength": 403.5,
      "relativeIntensity": 0.012589
    },
    {
      "wavelength": 404,
      "relativeIntensity": 0.012783
    },
    {
      "wavelength": 404.5,
      "relativeIntensity": 0.012944
    },
    {
      "wavelength": 405,
      "relativeIntensity": 0.013092
    },
    {
      "wavelength": 405.5,
      "relativeIntensity": 0.013274
    },
    {
      "wavelength": 406,
      "relativeIntensity": 0.013453
    },
    {
      "wavelength": 406.5,
      "relativeIntensity": 0.013583
    },
    {
      "wavelength": 407,
      "relativeIntensity": 0.013727
    },
    {
      "wavelength": 407.5,
      "relativeIntensity": 0.013819
    },
    {
      "wavelength": 408,
      "relativeIntensity": 0.013916
    },
    {
      "wavelength": 408.5,
      "relativeIntensity": 0.014077
    },
    {
      "wavelength": 409,
      "relativeIntensity": 0.01427
    },
    {
      "wavelength": 409.5,
      "relativeIntensity": 0.014456
    },
    {
      "wavelength": 410,
      "relativeIntensity": 0.014636
    },
    {
      "wavelength": 410.5,
      "relativeIntensity": 0.014779
    },
    {
      "wavelength": 411,
      "relativeIntensity": 0.01492
    },
    {
      "wavelength": 411.5,
      "relativeIntensity": 0.015107
    },
    {
      "wavelength": 412,
      "relativeIntensity": 0.015225
    },
    {
      "wavelength": 412.5,
      "relativeIntensity": 0.015378
    },
    {
      "wavelength": 413,
      "relativeIntensity": 0.015492
    },
    {
      "wavelength": 413.5,
      "relativeIntensity": 0.015652
    },
    {
      "wavelength": 414,
      "relativeIntensity": 0.01584
    },
    {
      "wavelength": 414.5,
      "relativeIntensity": 0.015969
    },
    {
      "wavelength": 415,
      "relativeIntensity": 0.016127
    },
    {
      "wavelength": 415.5,
      "relativeIntensity": 0.016344
    },
    {
      "wavelength": 416,
      "relativeIntensity": 0.016522
    },
    {
      "wavelength": 416.5,
      "relativeIntensity": 0.016697
    },
    {
      "wavelength": 417,
      "relativeIntensity": 0.016888
    },
    {
      "wavelength": 417.5,
      "relativeIntensity": 0.017048
    },
    {
      "wavelength": 418,
      "relativeIntensity": 0.017258
    },
    {
      "wavelength": 418.5,
      "relativeIntensity": 0.017434
    },
    {
      "wavelength": 419,
      "relativeIntensity": 0.017566
    },
    {
      "wavelength": 419.5,
      "relativeIntensity": 0.017709
    },
    {
      "wavelength": 420,
      "relativeIntensity": 0.017897
    },
    {
      "wavelength": 420.5,
      "relativeIntensity": 0.018075
    },
    {
      "wavelength": 421,
      "relativeIntensity": 0.018273
    },
    {
      "wavelength": 421.5,
      "relativeIntensity": 0.018358
    },
    {
      "wavelength": 422,
      "relativeIntensity": 0.018502
    },
    {
      "wavelength": 422.5,
      "relativeIntensity": 0.018738
    },
    {
      "wavelength": 423,
      "relativeIntensity": 0.018999
    },
    {
      "wavelength": 423.5,
      "relativeIntensity": 0.019306
    },
    {
      "wavelength": 424,
      "relativeIntensity": 0.019525
    },
    {
      "wavelength": 424.5,
      "relativeIntensity": 0.019611
    },
    {
      "wavelength": 425,
      "relativeIntensity": 0.019823
    },
    {
      "wavelength": 425.5,
      "relativeIntensity": 0.020029
    },
    {
      "wavelength": 426,
      "relativeIntensity": 0.020299
    },
    {
      "wavelength": 426.5,
      "relativeIntensity": 0.020549
    },
    {
      "wavelength": 427,
      "relativeIntensity": 0.020765
    },
    {
      "wavelength": 427.5,
      "relativeIntensity": 0.020951
    },
    {
      "wavelength": 428,
      "relativeIntensity": 0.021213
    },
    {
      "wavelength": 428.5,
      "relativeIntensity": 0.021366
    },
    {
      "wavelength": 429,
      "relativeIntensity": 0.021579
    },
    {
      "wavelength": 429.5,
      "relativeIntensity": 0.021778
    },
    {
      "wavelength": 430,
      "relativeIntensity": 0.021885
    },
    {
      "wavelength": 430.5,
      "relativeIntensity": 0.022098
    },
    {
      "wavelength": 431,
      "relativeIntensity": 0.02227
    },
    {
      "wavelength": 431.5,
      "relativeIntensity": 0.022508
    },
    {
      "wavelength": 432,
      "relativeIntensity": 0.02284
    },
    {
      "wavelength": 432.5,
      "relativeIntensity": 0.023099
    },
    {
      "wavelength": 433,
      "relativeIntensity": 0.023273
    },
    {
      "wavelength": 433.5,
      "relativeIntensity": 0.023354
    },
    {
      "wavelength": 434,
      "relativeIntensity": 0.023416
    },
    {
      "wavelength": 434.5,
      "relativeIntensity": 0.023588
    },
    {
      "wavelength": 435,
      "relativeIntensity": 0.023864
    },
    {
      "wavelength": 435.5,
      "relativeIntensity": 0.024215
    },
    {
      "wavelength": 436,
      "relativeIntensity": 0.024478
    },
    {
      "wavelength": 436.5,
      "relativeIntensity": 0.02471
    },
    {
      "wavelength": 437,
      "relativeIntensity": 0.024969
    },
    {
      "wavelength": 437.5,
      "relativeIntensity": 0.025294
    },
    {
      "wavelength": 438,
      "relativeIntensity": 0.025643
    },
    {
      "wavelength": 438.5,
      "relativeIntensity": 0.025855
    },
    {
      "wavelength": 439,
      "relativeIntensity": 0.026022
    },
    {
      "wavelength": 439.5,
      "relativeIntensity": 0.026159
    },
    {
      "wavelength": 440,
      "relativeIntensity": 0.026362
    },
    {
      "wavelength": 440.5,
      "relativeIntensity": 0.026678
    },
    {
      "wavelength": 441,
      "relativeIntensity": 0.026974
    },
    {
      "wavelength": 441.5,
      "relativeIntensity": 0.027269
    },
    {
      "wavelength": 442,
      "relativeIntensity": 0.027454
    },
    {
      "wavelength": 442.5,
      "relativeIntensity": 0.027571
    },
    {
      "wavelength": 443,
      "relativeIntensity": 0.027722
    },
    {
      "wavelength": 443.5,
      "relativeIntensity": 0.027841
    },
    {
      "wavelength": 444,
      "relativeIntensity": 0.028027
    },
    {
      "wavelength": 444.5,
      "relativeIntensity": 0.02826
    },
    {
      "wavelength": 445,
      "relativeIntensity": 0.028541
    },
    {
      "wavelength": 445.5,
      "relativeIntensity": 0.028854
    },
    {
      "wavelength": 446,
      "relativeIntensity": 0.029255
    },
    {
      "wavelength": 446.5,
      "relativeIntensity": 0.029523
    },
    {
      "wavelength": 447,
      "relativeIntensity": 0.029855
    },
    {
      "wavelength": 447.5,
      "relativeIntensity": 0.030155
    },
    {
      "wavelength": 448,
      "relativeIntensity": 0.030387
    },
    {
      "wavelength": 448.5,
      "relativeIntensity": 0.030566
    },
    {
      "wavelength": 449,
      "relativeIntensity": 0.030771
    },
    {
      "wavelength": 449.5,
      "relativeIntensity": 0.031009
    },
    {
      "wavelength": 450,
      "relativeIntensity": 0.031313
    },
    {
      "wavelength": 450.5,
      "relativeIntensity": 0.031644
    },
    {
      "wavelength": 451,
      "relativeIntensity": 0.031921
    },
    {
      "wavelength": 451.5,
      "relativeIntensity": 0.032134
    },
    {
      "wavelength": 452,
      "relativeIntensity": 0.03231
    },
    {
      "wavelength": 452.5,
      "relativeIntensity": 0.032525
    },
    {
      "wavelength": 453,
      "relativeIntensity": 0.032724
    },
    {
      "wavelength": 453.5,
      "relativeIntensity": 0.033004
    },
    {
      "wavelength": 454,
      "relativeIntensity": 0.033325
    },
    {
      "wavelength": 454.5,
      "relativeIntensity": 0.033568
    },
    {
      "wavelength": 455,
      "relativeIntensity": 0.033939
    },
    {
      "wavelength": 455.5,
      "relativeIntensity": 0.03419
    },
    {
      "wavelength": 456,
      "relativeIntensity": 0.034461
    },
    {
      "wavelength": 456.5,
      "relativeIntensity": 0.034826
    },
    {
      "wavelength": 457,
      "relativeIntensity": 0.035117
    },
    {
      "wavelength": 457.5,
      "relativeIntensity": 0.035479
    },
    {
      "wavelength": 458,
      "relativeIntensity": 0.035774
    },
    {
      "wavelength": 458.5,
      "relativeIntensity": 0.035983
    },
    {
      "wavelength": 459,
      "relativeIntensity": 0.036215
    },
    {
      "wavelength": 459.5,
      "relativeIntensity": 0.036382
    },
    {
      "wavelength": 460,
      "relativeIntensity": 0.036655
    },
    {
      "wavelength": 460.5,
      "relativeIntensity": 0.037032
    },
    {
      "wavelength": 461,
      "relativeIntensity": 0.037569
    },
    {
      "wavelength": 461.5,
      "relativeIntensity": 0.038002
    },
    {
      "wavelength": 462,
      "relativeIntensity": 0.038196
    },
    {
      "wavelength": 462.5,
      "relativeIntensity": 0.038409
    },
    {
      "wavelength": 463,
      "relativeIntensity": 0.038619
    },
    {
      "wavelength": 463.5,
      "relativeIntensity": 0.038963
    },
    {
      "wavelength": 464,
      "relativeIntensity": 0.039343
    },
    {
      "wavelength": 464.5,
      "relativeIntensity": 0.039618
    },
    {
      "wavelength": 465,
      "relativeIntensity": 0.03998
    },
    {
      "wavelength": 465.5,
      "relativeIntensity": 0.040362
    },
    {
      "wavelength": 466,
      "relativeIntensity": 0.040699
    },
    {
      "wavelength": 466.5,
      "relativeIntensity": 0.041033
    },
    {
      "wavelength": 467,
      "relativeIntensity": 0.041261
    },
    {
      "wavelength": 467.5,
      "relativeIntensity": 0.041467
    },
    {
      "wavelength": 468,
      "relativeIntensity": 0.041691
    },
    {
      "wavelength": 468.5,
      "relativeIntensity": 0.041974
    },
    {
      "wavelength": 469,
      "relativeIntensity": 0.042341
    },
    {
      "wavelength": 469.5,
      "relativeIntensity": 0.042611
    },
    {
      "wavelength": 470,
      "relativeIntensity": 0.042879
    },
    {
      "wavelength": 470.5,
      "relativeIntensity": 0.04311
    },
    {
      "wavelength": 471,
      "relativeIntensity": 0.043415
    },
    {
      "wavelength": 471.5,
      "relativeIntensity": 0.043733
    },
    {
      "wavelength": 472,
      "relativeIntensity": 0.044072
    },
    {
      "wavelength": 472.5,
      "relativeIntensity": 0.044427
    },
    {
      "wavelength": 473,
      "relativeIntensity": 0.044917
    },
    {
      "wavelength": 473.5,
      "relativeIntensity": 0.045385
    },
    {
      "wavelength": 474,
      "relativeIntensity": 0.045767
    },
    {
      "wavelength": 474.5,
      "relativeIntensity": 0.046128
    },
    {
      "wavelength": 475,
      "relativeIntensity": 0.04644
    },
    {
      "wavelength": 475.5,
      "relativeIntensity": 0.046773
    },
    {
      "wavelength": 476,
      "relativeIntensity": 0.047056
    },
    {
      "wavelength": 476.5,
      "relativeIntensity": 0.04732
    },
    {
      "wavelength": 477,
      "relativeIntensity": 0.047555
    },
    {
      "wavelength": 477.5,
      "relativeIntensity": 0.047847
    },
    {
      "wavelength": 478,
      "relativeIntensity": 0.048176
    },
    {
      "wavelength": 478.5,
      "relativeIntensity": 0.048648
    },
    {
      "wavelength": 479,
      "relativeIntensity": 0.049137
    },
    {
      "wavelength": 479.5,
      "relativeIntensity": 0.049623
    },
    {
      "wavelength": 480,
      "relativeIntensity": 0.050048
    },
    {
      "wavelength": 480.5,
      "relativeIntensity": 0.050285
    },
    {
      "wavelength": 481,
      "relativeIntensity": 0.050547
    },
    {
      "wavelength": 481.5,
      "relativeIntensity": 0.05075
    },
    {
      "wavelength": 482,
      "relativeIntensity": 0.051043
    },
    {
      "wavelength": 482.5,
      "relativeIntensity": 0.05144
    },
    {
      "wavelength": 483,
      "relativeIntensity": 0.051776
    },
    {
      "wavelength": 483.5,
      "relativeIntensity": 0.052154
    },
    {
      "wavelength": 484,
      "relativeIntensity": 0.052546
    },
    {
      "wavelength": 484.5,
      "relativeIntensity": 0.05286
    },
    {
      "wavelength": 485,
      "relativeIntensity": 0.053195
    },
    {
      "wavelength": 485.5,
      "relativeIntensity": 0.053397
    },
    {
      "wavelength": 486,
      "relativeIntensity": 0.05368
    },
    {
      "wavelength": 486.5,
      "relativeIntensity": 0.054066
    },
    {
      "wavelength": 487,
      "relativeIntensity": 0.05445
    },
    {
      "wavelength": 487.5,
      "relativeIntensity": 0.054859
    },
    {
      "wavelength": 488,
      "relativeIntensity": 0.055325
    },
    {
      "wavelength": 488.5,
      "relativeIntensity": 0.055765
    },
    {
      "wavelength": 489,
      "relativeIntensity": 0.056249
    },
    {
      "wavelength": 489.5,
      "relativeIntensity": 0.05663
    },
    {
      "wavelength": 490,
      "relativeIntensity": 0.05692
    },
    {
      "wavelength": 490.5,
      "relativeIntensity": 0.057265
    },
    {
      "wavelength": 491,
      "relativeIntensity": 0.057669
    },
    {
      "wavelength": 491.5,
      "relativeIntensity": 0.058006
    },
    {
      "wavelength": 492,
      "relativeIntensity": 0.058404
    },
    {
      "wavelength": 492.5,
      "relativeIntensity": 0.0588
    },
    {
      "wavelength": 493,
      "relativeIntensity": 0.059321
    },
    {
      "wavelength": 493.5,
      "relativeIntensity": 0.059936
    },
    {
      "wavelength": 494,
      "relativeIntensity": 0.060403
    },
    {
      "wavelength": 494.5,
      "relativeIntensity": 0.06083
    },
    {
      "wavelength": 495,
      "relativeIntensity": 0.061123
    },
    {
      "wavelength": 495.5,
      "relativeIntensity": 0.061453
    },
    {
      "wavelength": 496,
      "relativeIntensity": 0.061817
    },
    {
      "wavelength": 496.5,
      "relativeIntensity": 0.062307
    },
    {
      "wavelength": 497,
      "relativeIntensity": 0.062887
    },
    {
      "wavelength": 497.5,
      "relativeIntensity": 0.063467
    },
    {
      "wavelength": 498,
      "relativeIntensity": 0.063897
    },
    {
      "wavelength": 498.5,
      "relativeIntensity": 0.064274
    },
    {
      "wavelength": 499,
      "relativeIntensity": 0.06466
    },
    {
      "wavelength": 499.5,
      "relativeIntensity": 0.065168
    },
    {
      "wavelength": 500,
      "relativeIntensity": 0.065704
    },
    {
      "wavelength": 500.5,
      "relativeIntensity": 0.066111
    },
    {
      "wavelength": 501,
      "relativeIntensity": 0.066485
    },
    {
      "wavelength": 501.5,
      "relativeIntensity": 0.066868
    },
    {
      "wavelength": 502,
      "relativeIntensity": 0.067339
    },
    {
      "wavelength": 502.5,
      "relativeIntensity": 0.067816
    },
    {
      "wavelength": 503,
      "relativeIntensity": 0.068329
    },
    {
      "wavelength": 503.5,
      "relativeIntensity": 0.068913
    },
    {
      "wavelength": 504,
      "relativeIntensity": 0.069624
    },
    {
      "wavelength": 504.5,
      "relativeIntensity": 0.070275
    },
    {
      "wavelength": 505,
      "relativeIntensity": 0.070824
    },
    {
      "wavelength": 505.5,
      "relativeIntensity": 0.071282
    },
    {
      "wavelength": 506,
      "relativeIntensity": 0.071748
    },
    {
      "wavelength": 506.5,
      "relativeIntensity": 0.072255
    },
    {
      "wavelength": 507,
      "relativeIntensity": 0.072768
    },
    {
      "wavelength": 507.5,
      "relativeIntensity": 0.073332
    },
    {
      "wavelength": 508,
      "relativeIntensity": 0.07383
    },
    {
      "wavelength": 508.5,
      "relativeIntensity": 0.074442
    },
    {
      "wavelength": 509,
      "relativeIntensity": 0.074976
    },
    {
      "wavelength": 509.5,
      "relativeIntensity": 0.075526
    },
    {
      "wavelength": 510,
      "relativeIntensity": 0.076093
    },
    {
      "wavelength": 510.5,
      "relativeIntensity": 0.076639
    },
    {
      "wavelength": 511,
      "relativeIntensity": 0.077249
    },
    {
      "wavelength": 511.5,
      "relativeIntensity": 0.077859
    },
    {
      "wavelength": 512,
      "relativeIntensity": 0.078475
    },
    {
      "wavelength": 512.5,
      "relativeIntensity": 0.079112
    },
    {
      "wavelength": 513,
      "relativeIntensity": 0.079759
    },
    {
      "wavelength": 513.5,
      "relativeIntensity": 0.080302
    },
    {
      "wavelength": 514,
      "relativeIntensity": 0.080816
    },
    {
      "wavelength": 514.5,
      "relativeIntensity": 0.081427
    },
    {
      "wavelength": 515,
      "relativeIntensity": 0.082016
    },
    {
      "wavelength": 515.5,
      "relativeIntensity": 0.082645
    },
    {
      "wavelength": 516,
      "relativeIntensity": 0.083219
    },
    {
      "wavelength": 516.5,
      "relativeIntensity": 0.083789
    },
    {
      "wavelength": 517,
      "relativeIntensity": 0.084475
    },
    {
      "wavelength": 517.5,
      "relativeIntensity": 0.085144
    },
    {
      "wavelength": 518,
      "relativeIntensity": 0.085848
    },
    {
      "wavelength": 518.5,
      "relativeIntensity": 0.086589
    },
    {
      "wavelength": 519,
      "relativeIntensity": 0.087296
    },
    {
      "wavelength": 519.5,
      "relativeIntensity": 0.087861
    },
    {
      "wavelength": 520,
      "relativeIntensity": 0.08841
    },
    {
      "wavelength": 520.5,
      "relativeIntensity": 0.088874
    },
    {
      "wavelength": 521,
      "relativeIntensity": 0.08934
    },
    {
      "wavelength": 521.5,
      "relativeIntensity": 0.089917
    },
    {
      "wavelength": 522,
      "relativeIntensity": 0.090518
    },
    {
      "wavelength": 522.5,
      "relativeIntensity": 0.091271
    },
    {
      "wavelength": 523,
      "relativeIntensity": 0.091987
    },
    {
      "wavelength": 523.5,
      "relativeIntensity": 0.092676
    },
    {
      "wavelength": 524,
      "relativeIntensity": 0.093351
    },
    {
      "wavelength": 524.5,
      "relativeIntensity": 0.093975
    },
    {
      "wavelength": 525,
      "relativeIntensity": 0.09453
    },
    {
      "wavelength": 525.5,
      "relativeIntensity": 0.095039
    },
    {
      "wavelength": 526,
      "relativeIntensity": 0.095635
    },
    {
      "wavelength": 526.5,
      "relativeIntensity": 0.096353
    },
    {
      "wavelength": 527,
      "relativeIntensity": 0.097132
    },
    {
      "wavelength": 527.5,
      "relativeIntensity": 0.097868
    },
    {
      "wavelength": 528,
      "relativeIntensity": 0.098406
    },
    {
      "wavelength": 528.5,
      "relativeIntensity": 0.098971
    },
    {
      "wavelength": 529,
      "relativeIntensity": 0.099517
    },
    {
      "wavelength": 529.5,
      "relativeIntensity": 0.10015
    },
    {
      "wavelength": 530,
      "relativeIntensity": 0.10085
    },
    {
      "wavelength": 530.5,
      "relativeIntensity": 0.10152
    },
    {
      "wavelength": 531,
      "relativeIntensity": 0.10222
    },
    {
      "wavelength": 531.5,
      "relativeIntensity": 0.10286
    },
    {
      "wavelength": 532,
      "relativeIntensity": 0.10352
    },
    {
      "wavelength": 532.5,
      "relativeIntensity": 0.10413
    },
    {
      "wavelength": 533,
      "relativeIntensity": 0.10481
    },
    {
      "wavelength": 533.5,
      "relativeIntensity": 0.10543
    },
    {
      "wavelength": 534,
      "relativeIntensity": 0.10595
    },
    {
      "wavelength": 534.5,
      "relativeIntensity": 0.10644
    },
    {
      "wavelength": 535,
      "relativeIntensity": 0.10689
    },
    {
      "wavelength": 535.5,
      "relativeIntensity": 0.10748
    },
    {
      "wavelength": 536,
      "relativeIntensity": 0.10817
    },
    {
      "wavelength": 536.5,
      "relativeIntensity": 0.10894
    },
    {
      "wavelength": 537,
      "relativeIntensity": 0.10963
    },
    {
      "wavelength": 537.5,
      "relativeIntensity": 0.11026
    },
    {
      "wavelength": 538,
      "relativeIntensity": 0.11085
    },
    {
      "wavelength": 538.5,
      "relativeIntensity": 0.11139
    },
    {
      "wavelength": 539,
      "relativeIntensity": 0.11192
    },
    {
      "wavelength": 539.5,
      "relativeIntensity": 0.11241
    },
    {
      "wavelength": 540,
      "relativeIntensity": 0.11299
    },
    {
      "wavelength": 540.5,
      "relativeIntensity": 0.11368
    },
    {
      "wavelength": 541,
      "relativeIntensity": 0.11436
    },
    {
      "wavelength": 541.5,
      "relativeIntensity": 0.115
    },
    {
      "wavelength": 542,
      "relativeIntensity": 0.11561
    },
    {
      "wavelength": 542.5,
      "relativeIntensity": 0.11618
    },
    {
      "wavelength": 543,
      "relativeIntensity": 0.11674
    },
    {
      "wavelength": 543.5,
      "relativeIntensity": 0.11739
    },
    {
      "wavelength": 544,
      "relativeIntensity": 0.118
    },
    {
      "wavelength": 544.5,
      "relativeIntensity": 0.11863
    },
    {
      "wavelength": 545,
      "relativeIntensity": 0.11913
    },
    {
      "wavelength": 545.5,
      "relativeIntensity": 0.11953
    },
    {
      "wavelength": 546,
      "relativeIntensity": 0.11992
    },
    {
      "wavelength": 546.5,
      "relativeIntensity": 0.12043
    },
    {
      "wavelength": 547,
      "relativeIntensity": 0.12101
    },
    {
      "wavelength": 547.5,
      "relativeIntensity": 0.12165
    },
    {
      "wavelength": 548,
      "relativeIntensity": 0.12222
    },
    {
      "wavelength": 548.5,
      "relativeIntensity": 0.12283
    },
    {
      "wavelength": 549,
      "relativeIntensity": 0.12348
    },
    {
      "wavelength": 549.5,
      "relativeIntensity": 0.12405
    },
    {
      "wavelength": 550,
      "relativeIntensity": 0.12458
    },
    {
      "wavelength": 550.5,
      "relativeIntensity": 0.12515
    },
    {
      "wavelength": 551,
      "relativeIntensity": 0.12568
    },
    {
      "wavelength": 551.5,
      "relativeIntensity": 0.12628
    },
    {
      "wavelength": 552,
      "relativeIntensity": 0.12685
    },
    {
      "wavelength": 552.5,
      "relativeIntensity": 0.12745
    },
    {
      "wavelength": 553,
      "relativeIntensity": 0.12806
    },
    {
      "wavelength": 553.5,
      "relativeIntensity": 0.12866
    },
    {
      "wavelength": 554,
      "relativeIntensity": 0.12919
    },
    {
      "wavelength": 554.5,
      "relativeIntensity": 0.12968
    },
    {
      "wavelength": 555,
      "relativeIntensity": 0.13008
    },
    {
      "wavelength": 555.5,
      "relativeIntensity": 0.13056
    },
    {
      "wavelength": 556,
      "relativeIntensity": 0.1311
    },
    {
      "wavelength": 556.5,
      "relativeIntensity": 0.13177
    },
    {
      "wavelength": 557,
      "relativeIntensity": 0.1324
    },
    {
      "wavelength": 557.5,
      "relativeIntensity": 0.13301
    },
    {
      "wavelength": 558,
      "relativeIntensity": 0.13359
    },
    {
      "wavelength": 558.5,
      "relativeIntensity": 0.1342
    },
    {
      "wavelength": 559,
      "relativeIntensity": 0.1348
    },
    {
      "wavelength": 559.5,
      "relativeIntensity": 0.13536
    },
    {
      "wavelength": 560,
      "relativeIntensity": 0.13584
    },
    {
      "wavelength": 560.5,
      "relativeIntensity": 0.13626
    },
    {
      "wavelength": 561,
      "relativeIntensity": 0.13671
    },
    {
      "wavelength": 561.5,
      "relativeIntensity": 0.13713
    },
    {
      "wavelength": 562,
      "relativeIntensity": 0.13765
    },
    {
      "wavelength": 562.5,
      "relativeIntensity": 0.13817
    },
    {
      "wavelength": 563,
      "relativeIntensity": 0.13865
    },
    {
      "wavelength": 563.5,
      "relativeIntensity": 0.13912
    },
    {
      "wavelength": 564,
      "relativeIntensity": 0.1396
    },
    {
      "wavelength": 564.5,
      "relativeIntensity": 0.14013
    },
    {
      "wavelength": 565,
      "relativeIntensity": 0.14064
    },
    {
      "wavelength": 565.5,
      "relativeIntensity": 0.14111
    },
    {
      "wavelength": 566,
      "relativeIntensity": 0.14163
    },
    {
      "wavelength": 566.5,
      "relativeIntensity": 0.14221
    },
    {
      "wavelength": 567,
      "relativeIntensity": 0.1427
    },
    {
      "wavelength": 567.5,
      "relativeIntensity": 0.14314
    },
    {
      "wavelength": 568,
      "relativeIntensity": 0.14359
    },
    {
      "wavelength": 568.5,
      "relativeIntensity": 0.14409
    },
    {
      "wavelength": 569,
      "relativeIntensity": 0.14455
    },
    {
      "wavelength": 569.5,
      "relativeIntensity": 0.14493
    },
    {
      "wavelength": 570,
      "relativeIntensity": 0.14534
    },
    {
      "wavelength": 570.5,
      "relativeIntensity": 0.14585
    },
    {
      "wavelength": 571,
      "relativeIntensity": 0.14641
    },
    {
      "wavelength": 571.5,
      "relativeIntensity": 0.14688
    },
    {
      "wavelength": 572,
      "relativeIntensity": 0.14731
    },
    {
      "wavelength": 572.5,
      "relativeIntensity": 0.14777
    },
    {
      "wavelength": 573,
      "relativeIntensity": 0.14831
    },
    {
      "wavelength": 573.5,
      "relativeIntensity": 0.14881
    },
    {
      "wavelength": 574,
      "relativeIntensity": 0.14928
    },
    {
      "wavelength": 574.5,
      "relativeIntensity": 0.1498
    },
    {
      "wavelength": 575,
      "relativeIntensity": 0.15042
    },
    {
      "wavelength": 575.5,
      "relativeIntensity": 0.15101
    },
    {
      "wavelength": 576,
      "relativeIntensity": 0.15151
    },
    {
      "wavelength": 576.5,
      "relativeIntensity": 0.1519
    },
    {
      "wavelength": 577,
      "relativeIntensity": 0.15233
    },
    {
      "wavelength": 577.5,
      "relativeIntensity": 0.15276
    },
    {
      "wavelength": 578,
      "relativeIntensity": 0.15325
    },
    {
      "wavelength": 578.5,
      "relativeIntensity": 0.15377
    },
    {
      "wavelength": 579,
      "relativeIntensity": 0.15426
    },
    {
      "wavelength": 579.5,
      "relativeIntensity": 0.15474
    },
    {
      "wavelength": 580,
      "relativeIntensity": 0.15522
    },
    {
      "wavelength": 580.5,
      "relativeIntensity": 0.15576
    },
    {
      "wavelength": 581,
      "relativeIntensity": 0.1562
    },
    {
      "wavelength": 581.5,
      "relativeIntensity": 0.15663
    },
    {
      "wavelength": 582,
      "relativeIntensity": 0.157
    },
    {
      "wavelength": 582.5,
      "relativeIntensity": 0.15742
    },
    {
      "wavelength": 583,
      "relativeIntensity": 0.15786
    },
    {
      "wavelength": 583.5,
      "relativeIntensity": 0.15839
    },
    {
      "wavelength": 584,
      "relativeIntensity": 0.15893
    },
    {
      "wavelength": 584.5,
      "relativeIntensity": 0.15946
    },
    {
      "wavelength": 585,
      "relativeIntensity": 0.15984
    },
    {
      "wavelength": 585.5,
      "relativeIntensity": 0.16021
    },
    {
      "wavelength": 586,
      "relativeIntensity": 0.16059
    },
    {
      "wavelength": 586.5,
      "relativeIntensity": 0.16107
    },
    {
      "wavelength": 587,
      "relativeIntensity": 0.16153
    },
    {
      "wavelength": 587.5,
      "relativeIntensity": 0.16199
    },
    {
      "wavelength": 588,
      "relativeIntensity": 0.16246
    },
    {
      "wavelength": 588.5,
      "relativeIntensity": 0.163
    },
    {
      "wavelength": 589,
      "relativeIntensity": 0.16354
    },
    {
      "wavelength": 589.5,
      "relativeIntensity": 0.16408
    },
    {
      "wavelength": 590,
      "relativeIntensity": 0.16458
    },
    {
      "wavelength": 590.5,
      "relativeIntensity": 0.1651
    },
    {
      "wavelength": 591,
      "relativeIntensity": 0.16562
    },
    {
      "wavelength": 591.5,
      "relativeIntensity": 0.16608
    },
    {
      "wavelength": 592,
      "relativeIntensity": 0.16642
    },
    {
      "wavelength": 592.5,
      "relativeIntensity": 0.16667
    },
    {
      "wavelength": 593,
      "relativeIntensity": 0.167
    },
    {
      "wavelength": 593.5,
      "relativeIntensity": 0.16743
    },
    {
      "wavelength": 594,
      "relativeIntensity": 0.16801
    },
    {
      "wavelength": 594.5,
      "relativeIntensity": 0.16853
    },
    {
      "wavelength": 595,
      "relativeIntensity": 0.16903
    },
    {
      "wavelength": 595.5,
      "relativeIntensity": 0.1694
    },
    {
      "wavelength": 596,
      "relativeIntensity": 0.16981
    },
    {
      "wavelength": 596.5,
      "relativeIntensity": 0.17013
    },
    {
      "wavelength": 597,
      "relativeIntensity": 0.17054
    },
    {
      "wavelength": 597.5,
      "relativeIntensity": 0.17091
    },
    {
      "wavelength": 598,
      "relativeIntensity": 0.17129
    },
    {
      "wavelength": 598.5,
      "relativeIntensity": 0.17165
    },
    {
      "wavelength": 599,
      "relativeIntensity": 0.17206
    },
    {
      "wavelength": 599.5,
      "relativeIntensity": 0.17257
    },
    {
      "wavelength": 600,
      "relativeIntensity": 0.17311
    },
    {
      "wavelength": 600.5,
      "relativeIntensity": 0.1736
    },
    {
      "wavelength": 601,
      "relativeIntensity": 0.17404
    },
    {
      "wavelength": 601.5,
      "relativeIntensity": 0.17439
    },
    {
      "wavelength": 602,
      "relativeIntensity": 0.17474
    },
    {
      "wavelength": 602.5,
      "relativeIntensity": 0.17513
    },
    {
      "wavelength": 603,
      "relativeIntensity": 0.17552
    },
    {
      "wavelength": 603.5,
      "relativeIntensity": 0.17596
    },
    {
      "wavelength": 604,
      "relativeIntensity": 0.17638
    },
    {
      "wavelength": 604.5,
      "relativeIntensity": 0.17691
    },
    {
      "wavelength": 605,
      "relativeIntensity": 0.17734
    },
    {
      "wavelength": 605.5,
      "relativeIntensity": 0.17773
    },
    {
      "wavelength": 606,
      "relativeIntensity": 0.17804
    },
    {
      "wavelength": 606.5,
      "relativeIntensity": 0.17848
    },
    {
      "wavelength": 607,
      "relativeIntensity": 0.17903
    },
    {
      "wavelength": 607.5,
      "relativeIntensity": 0.17953
    },
    {
      "wavelength": 608,
      "relativeIntensity": 0.18003
    },
    {
      "wavelength": 608.5,
      "relativeIntensity": 0.18049
    },
    {
      "wavelength": 609,
      "relativeIntensity": 0.18097
    },
    {
      "wavelength": 609.5,
      "relativeIntensity": 0.18148
    },
    {
      "wavelength": 610,
      "relativeIntensity": 0.18198
    },
    {
      "wavelength": 610.5,
      "relativeIntensity": 0.18244
    },
    {
      "wavelength": 611,
      "relativeIntensity": 0.18283
    },
    {
      "wavelength": 611.5,
      "relativeIntensity": 0.18318
    },
    {
      "wavelength": 612,
      "relativeIntensity": 0.18362
    },
    {
      "wavelength": 612.5,
      "relativeIntensity": 0.18406
    },
    {
      "wavelength": 613,
      "relativeIntensity": 0.1845
    },
    {
      "wavelength": 613.5,
      "relativeIntensity": 0.18493
    },
    {
      "wavelength": 614,
      "relativeIntensity": 0.1854
    },
    {
      "wavelength": 614.5,
      "relativeIntensity": 0.18593
    },
    {
      "wavelength": 615,
      "relativeIntensity": 0.1865
    },
    {
      "wavelength": 615.5,
      "relativeIntensity": 0.18694
    },
    {
      "wavelength": 616,
      "relativeIntensity": 0.18728
    },
    {
      "wavelength": 616.5,
      "relativeIntensity": 0.18748
    },
    {
      "wavelength": 617,
      "relativeIntensity": 0.18788
    },
    {
      "wavelength": 617.5,
      "relativeIntensity": 0.18827
    },
    {
      "wavelength": 618,
      "relativeIntensity": 0.1888
    },
    {
      "wavelength": 618.5,
      "relativeIntensity": 0.18919
    },
    {
      "wavelength": 619,
      "relativeIntensity": 0.18955
    },
    {
      "wavelength": 619.5,
      "relativeIntensity": 0.1898
    },
    {
      "wavelength": 620,
      "relativeIntensity": 0.19018
    },
    {
      "wavelength": 620.5,
      "relativeIntensity": 0.19061
    },
    {
      "wavelength": 621,
      "relativeIntensity": 0.19133
    },
    {
      "wavelength": 621.5,
      "relativeIntensity": 0.19197
    },
    {
      "wavelength": 622,
      "relativeIntensity": 0.19256
    },
    {
      "wavelength": 622.5,
      "relativeIntensity": 0.1929
    },
    {
      "wavelength": 623,
      "relativeIntensity": 0.19309
    },
    {
      "wavelength": 623.5,
      "relativeIntensity": 0.19342
    },
    {
      "wavelength": 624,
      "relativeIntensity": 0.19381
    },
    {
      "wavelength": 624.5,
      "relativeIntensity": 0.19432
    },
    {
      "wavelength": 625,
      "relativeIntensity": 0.19472
    },
    {
      "wavelength": 625.5,
      "relativeIntensity": 0.19519
    },
    {
      "wavelength": 626,
      "relativeIntensity": 0.19553
    },
    {
      "wavelength": 626.5,
      "relativeIntensity": 0.19591
    },
    {
      "wavelength": 627,
      "relativeIntensity": 0.19628
    },
    {
      "wavelength": 627.5,
      "relativeIntensity": 0.19666
    },
    {
      "wavelength": 628,
      "relativeIntensity": 0.19706
    },
    {
      "wavelength": 628.5,
      "relativeIntensity": 0.1974
    },
    {
      "wavelength": 629,
      "relativeIntensity": 0.19791
    },
    {
      "wavelength": 629.5,
      "relativeIntensity": 0.19834
    },
    {
      "wavelength": 630,
      "relativeIntensity": 0.19886
    },
    {
      "wavelength": 630.5,
      "relativeIntensity": 0.19928
    },
    {
      "wavelength": 631,
      "relativeIntensity": 0.19973
    },
    {
      "wavelength": 631.5,
      "relativeIntensity": 0.20013
    },
    {
      "wavelength": 632,
      "relativeIntensity": 0.20031
    },
    {
      "wavelength": 632.5,
      "relativeIntensity": 0.2005
    },
    {
      "wavelength": 633,
      "relativeIntensity": 0.20075
    },
    {
      "wavelength": 633.5,
      "relativeIntensity": 0.2012
    },
    {
      "wavelength": 634,
      "relativeIntensity": 0.20171
    },
    {
      "wavelength": 634.5,
      "relativeIntensity": 0.20228
    },
    {
      "wavelength": 635,
      "relativeIntensity": 0.20282
    },
    {
      "wavelength": 635.5,
      "relativeIntensity": 0.20329
    },
    {
      "wavelength": 636,
      "relativeIntensity": 0.2036
    },
    {
      "wavelength": 636.5,
      "relativeIntensity": 0.20385
    },
    {
      "wavelength": 637,
      "relativeIntensity": 0.20427
    },
    {
      "wavelength": 637.5,
      "relativeIntensity": 0.20464
    },
    {
      "wavelength": 638,
      "relativeIntensity": 0.20504
    },
    {
      "wavelength": 638.5,
      "relativeIntensity": 0.20542
    },
    {
      "wavelength": 639,
      "relativeIntensity": 0.20576
    },
    {
      "wavelength": 639.5,
      "relativeIntensity": 0.20614
    },
    {
      "wavelength": 640,
      "relativeIntensity": 0.20651
    },
    {
      "wavelength": 640.5,
      "relativeIntensity": 0.20693
    },
    {
      "wavelength": 641,
      "relativeIntensity": 0.20729
    },
    {
      "wavelength": 641.5,
      "relativeIntensity": 0.20762
    },
    {
      "wavelength": 642,
      "relativeIntensity": 0.20801
    },
    {
      "wavelength": 642.5,
      "relativeIntensity": 0.2085
    },
    {
      "wavelength": 643,
      "relativeIntensity": 0.20889
    },
    {
      "wavelength": 643.5,
      "relativeIntensity": 0.20913
    },
    {
      "wavelength": 644,
      "relativeIntensity": 0.20943
    },
    {
      "wavelength": 644.5,
      "relativeIntensity": 0.20989
    },
    {
      "wavelength": 645,
      "relativeIntensity": 0.21041
    },
    {
      "wavelength": 645.5,
      "relativeIntensity": 0.21082
    },
    {
      "wavelength": 646,
      "relativeIntensity": 0.21098
    },
    {
      "wavelength": 646.5,
      "relativeIntensity": 0.21108
    },
    {
      "wavelength": 647,
      "relativeIntensity": 0.21139
    },
    {
      "wavelength": 647.5,
      "relativeIntensity": 0.21178
    },
    {
      "wavelength": 648,
      "relativeIntensity": 0.21235
    },
    {
      "wavelength": 648.5,
      "relativeIntensity": 0.21285
    },
    {
      "wavelength": 649,
      "relativeIntensity": 0.21341
    },
    {
      "wavelength": 649.5,
      "relativeIntensity": 0.21381
    },
    {
      "wavelength": 650,
      "relativeIntensity": 0.21406
    },
    {
      "wavelength": 650.5,
      "relativeIntensity": 0.2143
    },
    {
      "wavelength": 651,
      "relativeIntensity": 0.21463
    },
    {
      "wavelength": 651.5,
      "relativeIntensity": 0.21493
    },
    {
      "wavelength": 652,
      "relativeIntensity": 0.21513
    },
    {
      "wavelength": 652.5,
      "relativeIntensity": 0.21561
    },
    {
      "wavelength": 653,
      "relativeIntensity": 0.21609
    },
    {
      "wavelength": 653.5,
      "relativeIntensity": 0.21653
    },
    {
      "wavelength": 654,
      "relativeIntensity": 0.21686
    },
    {
      "wavelength": 654.5,
      "relativeIntensity": 0.21721
    },
    {
      "wavelength": 655,
      "relativeIntensity": 0.21773
    },
    {
      "wavelength": 655.5,
      "relativeIntensity": 0.21808
    },
    {
      "wavelength": 656,
      "relativeIntensity": 0.21846
    },
    {
      "wavelength": 656.5,
      "relativeIntensity": 0.21877
    },
    {
      "wavelength": 657,
      "relativeIntensity": 0.219
    },
    {
      "wavelength": 657.5,
      "relativeIntensity": 0.21935
    },
    {
      "wavelength": 658,
      "relativeIntensity": 0.21983
    },
    {
      "wavelength": 658.5,
      "relativeIntensity": 0.22034
    },
    {
      "wavelength": 659,
      "relativeIntensity": 0.22077
    },
    {
      "wavelength": 659.5,
      "relativeIntensity": 0.22115
    },
    {
      "wavelength": 660,
      "relativeIntensity": 0.22146
    },
    {
      "wavelength": 660.5,
      "relativeIntensity": 0.22192
    },
    {
      "wavelength": 661,
      "relativeIntensity": 0.2223
    },
    {
      "wavelength": 661.5,
      "relativeIntensity": 0.2227
    },
    {
      "wavelength": 662,
      "relativeIntensity": 0.22273
    },
    {
      "wavelength": 662.5,
      "relativeIntensity": 0.22291
    },
    {
      "wavelength": 663,
      "relativeIntensity": 0.22334
    },
    {
      "wavelength": 663.5,
      "relativeIntensity": 0.22389
    },
    {
      "wavelength": 664,
      "relativeIntensity": 0.22418
    },
    {
      "wavelength": 664.5,
      "relativeIntensity": 0.22431
    },
    {
      "wavelength": 665,
      "relativeIntensity": 0.22446
    },
    {
      "wavelength": 665.5,
      "relativeIntensity": 0.22478
    },
    {
      "wavelength": 666,
      "relativeIntensity": 0.22501
    },
    {
      "wavelength": 666.5,
      "relativeIntensity": 0.22541
    },
    {
      "wavelength": 667,
      "relativeIntensity": 0.22583
    },
    {
      "wavelength": 667.5,
      "relativeIntensity": 0.22633
    },
    {
      "wavelength": 668,
      "relativeIntensity": 0.22671
    },
    {
      "wavelength": 668.5,
      "relativeIntensity": 0.2272
    },
    {
      "wavelength": 669,
      "relativeIntensity": 0.22754
    },
    {
      "wavelength": 669.5,
      "relativeIntensity": 0.22781
    },
    {
      "wavelength": 670,
      "relativeIntensity": 0.22787
    },
    {
      "wavelength": 670.5,
      "relativeIntensity": 0.22823
    },
    {
      "wavelength": 671,
      "relativeIntensity": 0.22864
    },
    {
      "wavelength": 671.5,
      "relativeIntensity": 0.22894
    },
    {
      "wavelength": 672,
      "relativeIntensity": 0.22915
    },
    {
      "wavelength": 672.5,
      "relativeIntensity": 0.22947
    },
    {
      "wavelength": 673,
      "relativeIntensity": 0.22988
    },
    {
      "wavelength": 673.5,
      "relativeIntensity": 0.23017
    },
    {
      "wavelength": 674,
      "relativeIntensity": 0.23052
    },
    {
      "wavelength": 674.5,
      "relativeIntensity": 0.23108
    },
    {
      "wavelength": 675,
      "relativeIntensity": 0.23134
    },
    {
      "wavelength": 675.5,
      "relativeIntensity": 0.23142
    },
    {
      "wavelength": 676,
      "relativeIntensity": 0.23142
    },
    {
      "wavelength": 676.5,
      "relativeIntensity": 0.23184
    },
    {
      "wavelength": 677,
      "relativeIntensity": 0.23216
    },
    {
      "wavelength": 677.5,
      "relativeIntensity": 0.23267
    },
    {
      "wavelength": 678,
      "relativeIntensity": 0.23304
    },
    {
      "wavelength": 678.5,
      "relativeIntensity": 0.23357
    },
    {
      "wavelength": 679,
      "relativeIntensity": 0.2339
    },
    {
      "wavelength": 679.5,
      "relativeIntensity": 0.23431
    },
    {
      "wavelength": 680,
      "relativeIntensity": 0.23456
    },
    {
      "wavelength": 680.5,
      "relativeIntensity": 0.23488
    },
    {
      "wavelength": 681,
      "relativeIntensity": 0.23489
    },
    {
      "wavelength": 681.5,
      "relativeIntensity": 0.23496
    },
    {
      "wavelength": 682,
      "relativeIntensity": 0.23544
    },
    {
      "wavelength": 682.5,
      "relativeIntensity": 0.23617
    },
    {
      "wavelength": 683,
      "relativeIntensity": 0.23673
    },
    {
      "wavelength": 683.5,
      "relativeIntensity": 0.23672
    },
    {
      "wavelength": 684,
      "relativeIntensity": 0.23668
    },
    {
      "wavelength": 684.5,
      "relativeIntensity": 0.23681
    },
    {
      "wavelength": 685,
      "relativeIntensity": 0.23732
    },
    {
      "wavelength": 685.5,
      "relativeIntensity": 0.23811
    },
    {
      "wavelength": 686,
      "relativeIntensity": 0.23868
    },
    {
      "wavelength": 686.5,
      "relativeIntensity": 0.23903
    },
    {
      "wavelength": 687,
      "relativeIntensity": 0.23944
    },
    {
      "wavelength": 687.5,
      "relativeIntensity": 0.23981
    },
    {
      "wavelength": 688,
      "relativeIntensity": 0.2398
    },
    {
      "wavelength": 688.5,
      "relativeIntensity": 0.23987
    },
    {
      "wavelength": 689,
      "relativeIntensity": 0.23998
    },
    {
      "wavelength": 689.5,
      "relativeIntensity": 0.24043
    },
    {
      "wavelength": 690,
      "relativeIntensity": 0.24076
    },
    {
      "wavelength": 690.5,
      "relativeIntensity": 0.24111
    },
    {
      "wavelength": 691,
      "relativeIntensity": 0.2415
    },
    {
      "wavelength": 691.5,
      "relativeIntensity": 0.24221
    },
    {
      "wavelength": 692,
      "relativeIntensity": 0.24282
    },
    {
      "wavelength": 692.5,
      "relativeIntensity": 0.243
    },
    {
      "wavelength": 693,
      "relativeIntensity": 0.2429
    },
    {
      "wavelength": 693.5,
      "relativeIntensity": 0.24337
    },
    {
      "wavelength": 694,
      "relativeIntensity": 0.24398
    },
    {
      "wavelength": 694.5,
      "relativeIntensity": 0.24449
    },
    {
      "wavelength": 695,
      "relativeIntensity": 0.24476
    },
    {
      "wavelength": 695.5,
      "relativeIntensity": 0.24481
    },
    {
      "wavelength": 696,
      "relativeIntensity": 0.24471
    },
    {
      "wavelength": 696.5,
      "relativeIntensity": 0.24481
    },
    {
      "wavelength": 697,
      "relativeIntensity": 0.24542
    },
    {
      "wavelength": 697.5,
      "relativeIntensity": 0.24588
    },
    {
      "wavelength": 698,
      "relativeIntensity": 0.24573
    },
    {
      "wavelength": 698.5,
      "relativeIntensity": 0.24566
    },
    {
      "wavelength": 699,
      "relativeIntensity": 0.24574
    },
    {
      "wavelength": 699.5,
      "relativeIntensity": 0.2459
    },
    {
      "wavelength": 700,
      "relativeIntensity": 0.2462
    },
    {
      "wavelength": 700.5,
      "relativeIntensity": 0.24679
    },
    {
      "wavelength": 701,
      "relativeIntensity": 0.24774
    },
    {
      "wavelength": 701.5,
      "relativeIntensity": 0.24804
    },
    {
      "wavelength": 702,
      "relativeIntensity": 0.24822
    },
    {
      "wavelength": 702.5,
      "relativeIntensity": 0.24868
    },
    {
      "wavelength": 703,
      "relativeIntensity": 0.24945
    },
    {
      "wavelength": 703.5,
      "relativeIntensity": 0.25015
    },
    {
      "wavelength": 704,
      "relativeIntensity": 0.25049
    },
    {
      "wavelength": 704.5,
      "relativeIntensity": 0.25084
    },
    {
      "wavelength": 705,
      "relativeIntensity": 0.25073
    },
    {
      "wavelength": 705.5,
      "relativeIntensity": 0.25023
    },
    {
      "wavelength": 706,
      "relativeIntensity": 0.25016
    },
    {
      "wavelength": 706.5,
      "relativeIntensity": 0.25095
    },
    {
      "wavelength": 707,
      "relativeIntensity": 0.25155
    },
    {
      "wavelength": 707.5,
      "relativeIntensity": 0.25185
    },
    {
      "wavelength": 708,
      "relativeIntensity": 0.25184
    },
    {
      "wavelength": 708.5,
      "relativeIntensity": 0.25232
    },
    {
      "wavelength": 709,
      "relativeIntensity": 0.25245
    },
    {
      "wavelength": 709.5,
      "relativeIntensity": 0.25253
    },
    {
      "wavelength": 710,
      "relativeIntensity": 0.25239
    },
    {
      "wavelength": 710.5,
      "relativeIntensity": 0.2522
    },
    {
      "wavelength": 711,
      "relativeIntensity": 0.25222
    },
    {
      "wavelength": 711.5,
      "relativeIntensity": 0.25234
    },
    {
      "wavelength": 712,
      "relativeIntensity": 0.2528
    },
    {
      "wavelength": 712.5,
      "relativeIntensity": 0.25362
    },
    {
      "wavelength": 713,
      "relativeIntensity": 0.25451
    },
    {
      "wavelength": 713.5,
      "relativeIntensity": 0.25497
    },
    {
      "wavelength": 714,
      "relativeIntensity": 0.25514
    },
    {
      "wavelength": 714.5,
      "relativeIntensity": 0.25524
    },
    {
      "wavelength": 715,
      "relativeIntensity": 0.25542
    },
    {
      "wavelength": 715.5,
      "relativeIntensity": 0.25562
    },
    {
      "wavelength": 716,
      "relativeIntensity": 0.25602
    },
    {
      "wavelength": 716.5,
      "relativeIntensity": 0.25636
    },
    {
      "wavelength": 717,
      "relativeIntensity": 0.25645
    },
    {
      "wavelength": 717.5,
      "relativeIntensity": 0.25657
    },
    {
      "wavelength": 718,
      "relativeIntensity": 0.25695
    },
    {
      "wavelength": 718.5,
      "relativeIntensity": 0.25726
    },
    {
      "wavelength": 719,
      "relativeIntensity": 0.25777
    },
    {
      "wavelength": 719.5,
      "relativeIntensity": 0.25835
    },
    {
      "wavelength": 720,
      "relativeIntensity": 0.25873
    },
    {
      "wavelength": 720.5,
      "relativeIntensity": 0.25899
    },
    {
      "wavelength": 721,
      "relativeIntensity": 0.25876
    },
    {
      "wavelength": 721.5,
      "relativeIntensity": 0.25836
    },
    {
      "wavelength": 722,
      "relativeIntensity": 0.25811
    },
    {
      "wavelength": 722.5,
      "relativeIntensity": 0.25875
    },
    {
      "wavelength": 723,
      "relativeIntensity": 0.25956
    },
    {
      "wavelength": 723.5,
      "relativeIntensity": 0.25972
    },
    {
      "wavelength": 724,
      "relativeIntensity": 0.25965
    },
    {
      "wavelength": 724.5,
      "relativeIntensity": 0.25984
    },
    {
      "wavelength": 725,
      "relativeIntensity": 0.26067
    },
    {
      "wavelength": 725.5,
      "relativeIntensity": 0.26148
    },
    {
      "wavelength": 726,
      "relativeIntensity": 0.26159
    },
    {
      "wavelength": 726.5,
      "relativeIntensity": 0.26119
    },
    {
      "wavelength": 727,
      "relativeIntensity": 0.26102
    },
    {
      "wavelength": 727.5,
      "relativeIntensity": 0.26115
    },
    {
      "wavelength": 728,
      "relativeIntensity": 0.26129
    },
    {
      "wavelength": 728.5,
      "relativeIntensity": 0.26176
    },
    {
      "wavelength": 729,
      "relativeIntensity": 0.2628
    },
    {
      "wavelength": 729.5,
      "relativeIntensity": 0.26364
    },
    {
      "wavelength": 730,
      "relativeIntensity": 0.26383
    },
    {
      "wavelength": 730.5,
      "relativeIntensity": 0.26398
    },
    {
      "wavelength": 731,
      "relativeIntensity": 0.26418
    },
    {
      "wavelength": 731.5,
      "relativeIntensity": 0.26446
    },
    {
      "wavelength": 732,
      "relativeIntensity": 0.26456
    },
    {
      "wavelength": 732.5,
      "relativeIntensity": 0.26445
    },
    {
      "wavelength": 733,
      "relativeIntensity": 0.26469
    },
    {
      "wavelength": 733.5,
      "relativeIntensity": 0.26493
    },
    {
      "wavelength": 734,
      "relativeIntensity": 0.26566
    },
    {
      "wavelength": 734.5,
      "relativeIntensity": 0.26626
    },
    {
      "wavelength": 735,
      "relativeIntensity": 0.26713
    },
    {
      "wavelength": 735.5,
      "relativeIntensity": 0.26731
    },
    {
      "wavelength": 736,
      "relativeIntensity": 0.2668
    },
    {
      "wavelength": 736.5,
      "relativeIntensity": 0.26614
    },
    {
      "wavelength": 737,
      "relativeIntensity": 0.26575
    },
    {
      "wavelength": 737.5,
      "relativeIntensity": 0.26613
    },
    {
      "wavelength": 738,
      "relativeIntensity": 0.2667
    },
    {
      "wavelength": 738.5,
      "relativeIntensity": 0.26726
    },
    {
      "wavelength": 739,
      "relativeIntensity": 0.26734
    },
    {
      "wavelength": 739.5,
      "relativeIntensity": 0.26734
    },
    {
      "wavelength": 740,
      "relativeIntensity": 0.26758
    },
    {
      "wavelength": 740.5,
      "relativeIntensity": 0.26783
    },
    {
      "wavelength": 741,
      "relativeIntensity": 0.26836
    },
    {
      "wavelength": 741.5,
      "relativeIntensity": 0.26892
    },
    {
      "wavelength": 742,
      "relativeIntensity": 0.26925
    },
    {
      "wavelength": 742.5,
      "relativeIntensity": 0.26916
    },
    {
      "wavelength": 743,
      "relativeIntensity": 0.26972
    },
    {
      "wavelength": 743.5,
      "relativeIntensity": 0.27051
    },
    {
      "wavelength": 744,
      "relativeIntensity": 0.27085
    },
    {
      "wavelength": 744.5,
      "relativeIntensity": 0.27014
    },
    {
      "wavelength": 745,
      "relativeIntensity": 0.27002
    },
    {
      "wavelength": 745.5,
      "relativeIntensity": 0.27035
    },
    {
      "wavelength": 746,
      "relativeIntensity": 0.27099
    },
    {
      "wavelength": 746.5,
      "relativeIntensity": 0.27055
    },
    {
      "wavelength": 747,
      "relativeIntensity": 0.26998
    },
    {
      "wavelength": 747.5,
      "relativeIntensity": 0.2698
    },
    {
      "wavelength": 748,
      "relativeIntensity": 0.27038
    },
    {
      "wavelength": 748.5,
      "relativeIntensity": 0.27112
    },
    {
      "wavelength": 749,
      "relativeIntensity": 0.27184
    },
    {
      "wavelength": 749.5,
      "relativeIntensity": 0.27242
    },
    {
      "wavelength": 750,
      "relativeIntensity": 0.27304
    },
    {
      "wavelength": 750.5,
      "relativeIntensity": 0.27298
    },
    {
      "wavelength": 751,
      "relativeIntensity": 0.27266
    },
    {
      "wavelength": 751.5,
      "relativeIntensity": 0.27227
    },
    {
      "wavelength": 752,
      "relativeIntensity": 0.27142
    },
    {
      "wavelength": 752.5,
      "relativeIntensity": 0.27119
    },
    {
      "wavelength": 753,
      "relativeIntensity": 0.27152
    },
    {
      "wavelength": 753.5,
      "relativeIntensity": 0.27233
    },
    {
      "wavelength": 754,
      "relativeIntensity": 0.27236
    },
    {
      "wavelength": 754.5,
      "relativeIntensity": 0.27236
    },
    {
      "wavelength": 755,
      "relativeIntensity": 0.2723
    },
    {
      "wavelength": 755.5,
      "relativeIntensity": 0.27248
    },
    {
      "wavelength": 756,
      "relativeIntensity": 0.27265
    },
    {
      "wavelength": 756.5,
      "relativeIntensity": 0.27267
    },
    {
      "wavelength": 757,
      "relativeIntensity": 0.27256
    },
    {
      "wavelength": 757.5,
      "relativeIntensity": 0.27219
    },
    {
      "wavelength": 758,
      "relativeIntensity": 0.27256
    },
    {
      "wavelength": 758.5,
      "relativeIntensity": 0.27301
    },
    {
      "wavelength": 759,
      "relativeIntensity": 0.27373
    },
    {
      "wavelength": 759.5,
      "relativeIntensity": 0.27384
    },
    {
      "wavelength": 760,
      "relativeIntensity": 0.27399
    },
    {
      "wavelength": 760.5,
      "relativeIntensity": 0.27378
    },
    {
      "wavelength": 761,
      "relativeIntensity": 0.27405
    },
    {
      "wavelength": 761.5,
      "relativeIntensity": 0.27399
    },
    {
      "wavelength": 762,
      "relativeIntensity": 0.27443
    },
    {
      "wavelength": 762.5,
      "relativeIntensity": 0.2749
    },
    {
      "wavelength": 763,
      "relativeIntensity": 0.2747
    },
    {
      "wavelength": 763.5,
      "relativeIntensity": 0.27475
    },
    {
      "wavelength": 764,
      "relativeIntensity": 0.2747
    },
    {
      "wavelength": 764.5,
      "relativeIntensity": 0.27523
    },
    {
      "wavelength": 765,
      "relativeIntensity": 0.27533
    },
    {
      "wavelength": 765.5,
      "relativeIntensity": 0.27526
    },
    {
      "wavelength": 766,
      "relativeIntensity": 0.27516
    },
    {
      "wavelength": 766.5,
      "relativeIntensity": 0.27587
    },
    {
      "wavelength": 767,
      "relativeIntensity": 0.27584
    },
    {
      "wavelength": 767.5,
      "relativeIntensity": 0.27568
    },
    {
      "wavelength": 768,
      "relativeIntensity": 0.27623
    },
    {
      "wavelength": 768.5,
      "relativeIntensity": 0.27703
    },
    {
      "wavelength": 769,
      "relativeIntensity": 0.27713
    },
    {
      "wavelength": 769.5,
      "relativeIntensity": 0.27652
    },
    {
      "wavelength": 770,
      "relativeIntensity": 0.27671
    },
    {
      "wavelength": 770.5,
      "relativeIntensity": 0.27694
    },
    {
      "wavelength": 771,
      "relativeIntensity": 0.27659
    },
    {
      "wavelength": 771.5,
      "relativeIntensity": 0.27599
    },
    {
      "wavelength": 772,
      "relativeIntensity": 0.2763
    },
    {
      "wavelength": 772.5,
      "relativeIntensity": 0.27658
    },
    {
      "wavelength": 773,
      "relativeIntensity": 0.27655
    },
    {
      "wavelength": 773.5,
      "relativeIntensity": 0.27602
    },
    {
      "wavelength": 774,
      "relativeIntensity": 0.27598
    },
    {
      "wavelength": 774.5,
      "relativeIntensity": 0.27683
    },
    {
      "wavelength": 775,
      "relativeIntensity": 0.27738
    },
    {
      "wavelength": 775.5,
      "relativeIntensity": 0.27784
    },
    {
      "wavelength": 776,
      "relativeIntensity": 0.27805
    },
    {
      "wavelength": 776.5,
      "relativeIntensity": 0.27837
    },
    {
      "wavelength": 777,
      "relativeIntensity": 0.27791
    },
    {
      "wavelength": 777.5,
      "relativeIntensity": 0.27808
    },
    {
      "wavelength": 778,
      "relativeIntensity": 0.2777
    },
    {
      "wavelength": 778.5,
      "relativeIntensity": 0.27813
    },
    {
      "wavelength": 779,
      "relativeIntensity": 0.27783
    },
    {
      "wavelength": 779.5,
      "relativeIntensity": 0.27791
    },
    {
      "wavelength": 780,
      "relativeIntensity": 0.27772
    },
    {
      "wavelength": 780.5,
      "relativeIntensity": 0.27834
    },
    {
      "wavelength": 781,
      "relativeIntensity": 0.27874
    },
    {
      "wavelength": 781.5,
      "relativeIntensity": 0.27957
    },
    {
      "wavelength": 782,
      "relativeIntensity": 0.27997
    },
    {
      "wavelength": 782.5,
      "relativeIntensity": 0.28058
    },
    {
      "wavelength": 783,
      "relativeIntensity": 0.28011
    },
    {
      "wavelength": 783.5,
      "relativeIntensity": 0.28019
    },
    {
      "wavelength": 784,
      "relativeIntensity": 0.28053
    },
    {
      "wavelength": 784.5,
      "relativeIntensity": 0.28172
    },
    {
      "wavelength": 785,
      "relativeIntensity": 0.28194
    },
    {
      "wavelength": 785.5,
      "relativeIntensity": 0.28173
    },
    {
      "wavelength": 786,
      "relativeIntensity": 0.281
    },
    {
      "wavelength": 786.5,
      "relativeIntensity": 0.28098
    },
    {
      "wavelength": 787,
      "relativeIntensity": 0.28066
    },
    {
      "wavelength": 787.5,
      "relativeIntensity": 0.28055
    },
    {
      "wavelength": 788,
      "relativeIntensity": 0.28033
    },
    {
      "wavelength": 788.5,
      "relativeIntensity": 0.28034
    },
    {
      "wavelength": 789,
      "relativeIntensity": 0.28075
    },
    {
      "wavelength": 789.5,
      "relativeIntensity": 0.2818
    },
    {
      "wavelength": 790,
      "relativeIntensity": 0.28245
    },
    {
      "wavelength": 790.5,
      "relativeIntensity": 0.2819
    },
    {
      "wavelength": 791,
      "relativeIntensity": 0.28175
    },
    {
      "wavelength": 791.5,
      "relativeIntensity": 0.28212
    },
    {
      "wavelength": 792,
      "relativeIntensity": 0.28269
    },
    {
      "wavelength": 792.5,
      "relativeIntensity": 0.28262
    },
    {
      "wavelength": 793,
      "relativeIntensity": 0.2832
    },
    {
      "wavelength": 793.5,
      "relativeIntensity": 0.28359
    },
    {
      "wavelength": 794,
      "relativeIntensity": 0.28398
    },
    {
      "wavelength": 794.5,
      "relativeIntensity": 0.28371
    },
    {
      "wavelength": 795,
      "relativeIntensity": 0.28351
    },
    {
      "wavelength": 795.5,
      "relativeIntensity": 0.28287
    },
    {
      "wavelength": 796,
      "relativeIntensity": 0.28303
    },
    {
      "wavelength": 796.5,
      "relativeIntensity": 0.28371
    },
    {
      "wavelength": 797,
      "relativeIntensity": 0.28425
    },
    {
      "wavelength": 797.5,
      "relativeIntensity": 0.28439
    },
    {
      "wavelength": 798,
      "relativeIntensity": 0.28428
    },
    {
      "wavelength": 798.5,
      "relativeIntensity": 0.28482
    },
    {
      "wavelength": 799,
      "relativeIntensity": 0.2855
    },
    {
      "wavelength": 799.5,
      "relativeIntensity": 0.28661
    },
    {
      "wavelength": 800,
      "relativeIntensity": 0.28681
    },
    {
      "wavelength": 800.5,
      "relativeIntensity": 0.28719
    },
    {
      "wavelength": 801,
      "relativeIntensity": 0.28691
    },
    {
      "wavelength": 801.5,
      "relativeIntensity": 0.28644
    },
    {
      "wavelength": 802,
      "relativeIntensity": 0.28668
    },
    {
      "wavelength": 802.5,
      "relativeIntensity": 0.28723
    },
    {
      "wavelength": 803,
      "relativeIntensity": 0.28707
    },
    {
      "wavelength": 803.5,
      "relativeIntensity": 0.28607
    },
    {
      "wavelength": 804,
      "relativeIntensity": 0.28513
    },
    {
      "wavelength": 804.5,
      "relativeIntensity": 0.28502
    },
    {
      "wavelength": 805,
      "relativeIntensity": 0.28655
    },
    {
      "wavelength": 805.5,
      "relativeIntensity": 0.28852
    },
    {
      "wavelength": 806,
      "relativeIntensity": 0.28884
    },
    {
      "wavelength": 806.5,
      "relativeIntensity": 0.2878
    },
    {
      "wavelength": 807,
      "relativeIntensity": 0.28694
    },
    {
      "wavelength": 807.5,
      "relativeIntensity": 0.287
    },
    {
      "wavelength": 808,
      "relativeIntensity": 0.28792
    },
    {
      "wavelength": 808.5,
      "relativeIntensity": 0.28851
    },
    {
      "wavelength": 809,
      "relativeIntensity": 0.28926
    },
    {
      "wavelength": 809.5,
      "relativeIntensity": 0.28904
    },
    {
      "wavelength": 810,
      "relativeIntensity": 0.28902
    },
    {
      "wavelength": 810.5,
      "relativeIntensity": 0.28931
    },
    {
      "wavelength": 811,
      "relativeIntensity": 0.2894
    },
    {
      "wavelength": 811.5,
      "relativeIntensity": 0.28935
    },
    {
      "wavelength": 812,
      "relativeIntensity": 0.28934
    },
    {
      "wavelength": 812.5,
      "relativeIntensity": 0.29002
    },
    {
      "wavelength": 813,
      "relativeIntensity": 0.29129
    },
    {
      "wavelength": 813.5,
      "relativeIntensity": 0.29215
    },
    {
      "wavelength": 814,
      "relativeIntensity": 0.29173
    },
    {
      "wavelength": 814.5,
      "relativeIntensity": 0.29123
    },
    {
      "wavelength": 815,
      "relativeIntensity": 0.2911
    },
    {
      "wavelength": 815.5,
      "relativeIntensity": 0.29119
    },
    {
      "wavelength": 816,
      "relativeIntensity": 0.29127
    },
    {
      "wavelength": 816.5,
      "relativeIntensity": 0.29234
    },
    {
      "wavelength": 817,
      "relativeIntensity": 0.29283
    },
    {
      "wavelength": 817.5,
      "relativeIntensity": 0.29225
    },
    {
      "wavelength": 818,
      "relativeIntensity": 0.29139
    },
    {
      "wavelength": 818.5,
      "relativeIntensity": 0.2919
    },
    {
      "wavelength": 819,
      "relativeIntensity": 0.29276
    },
    {
      "wavelength": 819.5,
      "relativeIntensity": 0.29192
    },
    {
      "wavelength": 820,
      "relativeIntensity": 0.29215
    },
    {
      "wavelength": 820.5,
      "relativeIntensity": 0.29162
    },
    {
      "wavelength": 821,
      "relativeIntensity": 0.29195
    },
    {
      "wavelength": 821.5,
      "relativeIntensity": 0.2911
    },
    {
      "wavelength": 822,
      "relativeIntensity": 0.2917
    },
    {
      "wavelength": 822.5,
      "relativeIntensity": 0.29339
    },
    {
      "wavelength": 823,
      "relativeIntensity": 0.29451
    },
    {
      "wavelength": 823.5,
      "relativeIntensity": 0.29353
    },
    {
      "wavelength": 824,
      "relativeIntensity": 0.29304
    },
    {
      "wavelength": 824.5,
      "relativeIntensity": 0.29331
    },
    {
      "wavelength": 825,
      "relativeIntensity": 0.29353
    },
    {
      "wavelength": 825.5,
      "relativeIntensity": 0.29342
    },
    {
      "wavelength": 826,
      "relativeIntensity": 0.29392
    },
    {
      "wavelength": 826.5,
      "relativeIntensity": 0.29419
    },
    {
      "wavelength": 827,
      "relativeIntensity": 0.29361
    },
    {
      "wavelength": 827.5,
      "relativeIntensity": 0.29405
    },
    {
      "wavelength": 828,
      "relativeIntensity": 0.29421
    },
    {
      "wavelength": 828.5,
      "relativeIntensity": 0.29422
    },
    {
      "wavelength": 829,
      "relativeIntensity": 0.29445
    },
    {
      "wavelength": 829.5,
      "relativeIntensity": 0.29491
    },
    {
      "wavelength": 830,
      "relativeIntensity": 0.29503
    },
    {
      "wavelength": 830.5,
      "relativeIntensity": 0.29411
    },
    {
      "wavelength": 831,
      "relativeIntensity": 0.29346
    },
    {
      "wavelength": 831.5,
      "relativeIntensity": 0.29384
    },
    {
      "wavelength": 832,
      "relativeIntensity": 0.29474
    },
    {
      "wavelength": 832.5,
      "relativeIntensity": 0.29593
    },
    {
      "wavelength": 833,
      "relativeIntensity": 0.29704
    },
    {
      "wavelength": 833.5,
      "relativeIntensity": 0.29631
    },
    {
      "wavelength": 834,
      "relativeIntensity": 0.29562
    },
    {
      "wavelength": 834.5,
      "relativeIntensity": 0.2968
    },
    {
      "wavelength": 835,
      "relativeIntensity": 0.29737
    },
    {
      "wavelength": 835.5,
      "relativeIntensity": 0.29706
    },
    {
      "wavelength": 836,
      "relativeIntensity": 0.2968
    },
    {
      "wavelength": 836.5,
      "relativeIntensity": 0.29616
    },
    {
      "wavelength": 837,
      "relativeIntensity": 0.2961
    },
    {
      "wavelength": 837.5,
      "relativeIntensity": 0.29713
    },
    {
      "wavelength": 838,
      "relativeIntensity": 0.2984
    },
    {
      "wavelength": 838.5,
      "relativeIntensity": 0.2994
    },
    {
      "wavelength": 839,
      "relativeIntensity": 0.29937
    },
    {
      "wavelength": 839.5,
      "relativeIntensity": 0.30014
    },
    {
      "wavelength": 840,
      "relativeIntensity": 0.30046
    },
    {
      "wavelength": 840.5,
      "relativeIntensity": 0.29864
    },
    {
      "wavelength": 841,
      "relativeIntensity": 0.29721
    },
    {
      "wavelength": 841.5,
      "relativeIntensity": 0.29741
    },
    {
      "wavelength": 842,
      "relativeIntensity": 0.29757
    },
    {
      "wavelength": 842.5,
      "relativeIntensity": 0.29695
    },
    {
      "wavelength": 843,
      "relativeIntensity": 0.29694
    },
    {
      "wavelength": 843.5,
      "relativeIntensity": 0.29881
    },
    {
      "wavelength": 844,
      "relativeIntensity": 0.29996
    },
    {
      "wavelength": 844.5,
      "relativeIntensity": 0.30062
    },
    {
      "wavelength": 845,
      "relativeIntensity": 0.30117
    },
    {
      "wavelength": 845.5,
      "relativeIntensity": 0.3018
    },
    {
      "wavelength": 846,
      "relativeIntensity": 0.3007
    },
    {
      "wavelength": 846.5,
      "relativeIntensity": 0.30072
    },
    {
      "wavelength": 847,
      "relativeIntensity": 0.30041
    },
    {
      "wavelength": 847.5,
      "relativeIntensity": 0.30031
    },
    {
      "wavelength": 848,
      "relativeIntensity": 0.30076
    },
    {
      "wavelength": 848.5,
      "relativeIntensity": 0.30274
    },
    {
      "wavelength": 849,
      "relativeIntensity": 0.30337
    },
    {
      "wavelength": 849.5,
      "relativeIntensity": 0.30305
    },
    {
      "wavelength": 850,
      "relativeIntensity": 0.30174
    },
    {
      "wavelength": 850.5,
      "relativeIntensity": 0.30302
    },
    {
      "wavelength": 851,
      "relativeIntensity": 0.30469
    },
    {
      "wavelength": 851.5,
      "relativeIntensity": 0.30373
    },
    {
      "wavelength": 852,
      "relativeIntensity": 0.30269
    },
    {
      "wavelength": 852.5,
      "relativeIntensity": 0.30165
    },
    {
      "wavelength": 853,
      "relativeIntensity": 0.30238
    },
    {
      "wavelength": 853.5,
      "relativeIntensity": 0.30386
    },
    {
      "wavelength": 854,
      "relativeIntensity": 0.30425
    },
    {
      "wavelength": 854.5,
      "relativeIntensity": 0.30271
    },
    {
      "wavelength": 855,
      "relativeIntensity": 0.30315
    },
    {
      "wavelength": 855.5,
      "relativeIntensity": 0.30489
    },
    {
      "wavelength": 856,
      "relativeIntensity": 0.30607
    },
    {
      "wavelength": 856.5,
      "relativeIntensity": 0.30553
    },
    {
      "wavelength": 857,
      "relativeIntensity": 0.30453
    },
    {
      "wavelength": 857.5,
      "relativeIntensity": 0.30458
    },
    {
      "wavelength": 858,
      "relativeIntensity": 0.30662
    },
    {
      "wavelength": 858.5,
      "relativeIntensity": 0.30789
    },
    {
      "wavelength": 859,
      "relativeIntensity": 0.30806
    },
    {
      "wavelength": 859.5,
      "relativeIntensity": 0.30785
    },
    {
      "wavelength": 860,
      "relativeIntensity": 0.30864
    },
    {
      "wavelength": 860.5,
      "relativeIntensity": 0.30934
    },
    {
      "wavelength": 861,
      "relativeIntensity": 0.30894
    },
    {
      "wavelength": 861.5,
      "relativeIntensity": 0.30819
    },
    {
      "wavelength": 862,
      "relativeIntensity": 0.30837
    },
    {
      "wavelength": 862.5,
      "relativeIntensity": 0.30961
    },
    {
      "wavelength": 863,
      "relativeIntensity": 0.31153
    },
    {
      "wavelength": 863.5,
      "relativeIntensity": 0.31196
    },
    {
      "wavelength": 864,
      "relativeIntensity": 0.30972
    },
    {
      "wavelength": 864.5,
      "relativeIntensity": 0.30914
    },
    {
      "wavelength": 865,
      "relativeIntensity": 0.31072
    },
    {
      "wavelength": 865.5,
      "relativeIntensity": 0.31228
    },
    {
      "wavelength": 866,
      "relativeIntensity": 0.31422
    },
    {
      "wavelength": 866.5,
      "relativeIntensity": 0.31424
    },
    {
      "wavelength": 867,
      "relativeIntensity": 0.31377
    },
    {
      "wavelength": 867.5,
      "relativeIntensity": 0.31274
    },
    {
      "wavelength": 868,
      "relativeIntensity": 0.31218
    },
    {
      "wavelength": 868.5,
      "relativeIntensity": 0.31278
    },
    {
      "wavelength": 869,
      "relativeIntensity": 0.31272
    },
    {
      "wavelength": 869.5,
      "relativeIntensity": 0.31384
    },
    {
      "wavelength": 870,
      "relativeIntensity": 0.3146
    },
    {
      "wavelength": 870.5,
      "relativeIntensity": 0.31349
    },
    {
      "wavelength": 871,
      "relativeIntensity": 0.31215
    },
    {
      "wavelength": 871.5,
      "relativeIntensity": 0.31475
    },
    {
      "wavelength": 872,
      "relativeIntensity": 0.31694
    },
    {
      "wavelength": 872.5,
      "relativeIntensity": 0.31669
    },
    {
      "wavelength": 873,
      "relativeIntensity": 0.31529
    },
    {
      "wavelength": 873.5,
      "relativeIntensity": 0.31506
    },
    {
      "wavelength": 874,
      "relativeIntensity": 0.31582
    },
    {
      "wavelength": 874.5,
      "relativeIntensity": 0.31584
    },
    {
      "wavelength": 875,
      "relativeIntensity": 0.31645
    },
    {
      "wavelength": 875.5,
      "relativeIntensity": 0.31891
    },
    {
      "wavelength": 876,
      "relativeIntensity": 0.32023
    },
    {
      "wavelength": 876.5,
      "relativeIntensity": 0.31918
    },
    {
      "wavelength": 877,
      "relativeIntensity": 0.31932
    },
    {
      "wavelength": 877.5,
      "relativeIntensity": 0.32157
    },
    {
      "wavelength": 878,
      "relativeIntensity": 0.32295
    },
    {
      "wavelength": 878.5,
      "relativeIntensity": 0.32345
    },
    {
      "wavelength": 879,
      "relativeIntensity": 0.32376
    },
    {
      "wavelength": 879.5,
      "relativeIntensity": 0.32165
    },
    {
      "wavelength": 880,
      "relativeIntensity": 0.31745
    },
    {
      "wavelength": 880.5,
      "relativeIntensity": 0.31779
    },
    {
      "wavelength": 881,
      "relativeIntensity": 0.32164
    },
    {
      "wavelength": 881.5,
      "relativeIntensity": 0.32231
    },
    {
      "wavelength": 882,
      "relativeIntensity": 0.32006
    },
    {
      "wavelength": 882.5,
      "relativeIntensity": 0.31853
    },
    {
      "wavelength": 883,
      "relativeIntensity": 0.32058
    },
    {
      "wavelength": 883.5,
      "relativeIntensity": 0.32225
    },
    {
      "wavelength": 884,
      "relativeIntensity": 0.32359
    },
    {
      "wavelength": 884.5,
      "relativeIntensity": 0.32504
    },
    {
      "wavelength": 885,
      "relativeIntensity": 0.32456
    },
    {
      "wavelength": 885.5,
      "relativeIntensity": 0.32404
    },
    {
      "wavelength": 886,
      "relativeIntensity": 0.32694
    },
    {
      "wavelength": 886.5,
      "relativeIntensity": 0.32794
    },
    {
      "wavelength": 887,
      "relativeIntensity": 0.32722
    },
    {
      "wavelength": 887.5,
      "relativeIntensity": 0.32718
    },
    {
      "wavelength": 888,
      "relativeIntensity": 0.32685
    },
    {
      "wavelength": 888.5,
      "relativeIntensity": 0.32628
    },
    {
      "wavelength": 889,
      "relativeIntensity": 0.32684
    },
    {
      "wavelength": 889.5,
      "relativeIntensity": 0.32644
    },
    {
      "wavelength": 890,
      "relativeIntensity": 0.32559
    },
    {
      "wavelength": 890.5,
      "relativeIntensity": 0.32533
    },
    {
      "wavelength": 891,
      "relativeIntensity": 0.32496
    },
    {
      "wavelength": 891.5,
      "relativeIntensity": 0.32491
    },
    {
      "wavelength": 892,
      "relativeIntensity": 0.3267
    },
    {
      "wavelength": 892.5,
      "relativeIntensity": 0.32791
    },
    {
      "wavelength": 893,
      "relativeIntensity": 0.32689
    },
    {
      "wavelength": 893.5,
      "relativeIntensity": 0.32531
    },
    {
      "wavelength": 894,
      "relativeIntensity": 0.32465
    },
    {
      "wavelength": 894.5,
      "relativeIntensity": 0.32554
    },
    {
      "wavelength": 895,
      "relativeIntensity": 0.32479
    },
    {
      "wavelength": 895.5,
      "relativeIntensity": 0.32393
    },
    {
      "wavelength": 896,
      "relativeIntensity": 0.32449
    },
    {
      "wavelength": 896.5,
      "relativeIntensity": 0.32703
    },
    {
      "wavelength": 897,
      "relativeIntensity": 0.32741
    },
    {
      "wavelength": 897.5,
      "relativeIntensity": 0.32702
    },
    {
      "wavelength": 898,
      "relativeIntensity": 0.32792
    },
    {
      "wavelength": 898.5,
      "relativeIntensity": 0.32936
    },
    {
      "wavelength": 899,
      "relativeIntensity": 0.329
    },
    {
      "wavelength": 899.5,
      "relativeIntensity": 0.0065015
    },
    {
      "wavelength": null,
      "relativeIntensity": null
    },
    {
      "wavelength": null,
      "relativeIntensity": null
    }
  ]
}
